{
  "year": "1996",
  "entity": "TI",
  "total": 19,
  "categorized": 19,
  "uncategorized": 0,
  "by_type": {
    "Regolamento": {
      "total": 6,
      "by_topic": {
        "A1.4 ORDINE PUBBLICO": 1,
        "A11.3 SVILUPPO ECONOMICO E MISURE A FAVORE DEI SINGOLI RAMI ECONOMICI": 1,
        "A2.5 AMMINISTRAZIONE CANTONALE": 1,
        "A5.1 SCUOLA": 1,
        "A8.1 AGRICOLTURA": 1,
        "811 Stabilimenti ospedalieri": 1
      },
      "by_global_category": {
        "9.50.10.10 Professioni che necessitano un'autorizzazione": 1,
        "1.20.20.40.50 Pensioni, previdenza, assicurazione": 1,
        "4.140 Riconoscimento dei diplomi": 1,
        "2.20.10.20.10 Affitto agricolo": 1
      }
    },
    "Legge": {
      "total": 6,
      "by_topic": {
        "A1.4 ORDINE PUBBLICO": 1,
        "215 Diritti reali": 1,
        "A5.1 SCUOLA": 1,
        "A8.5 CACCIA E PESCA": 1,
        "824 Derrate alimentari e oggetti d’uso": 1,
        "835 Protezione dagli incendi": 1
      },
      "by_global_category": {
        "2.10.40.10 Estimazione ufficiale dei fondi": 1,
        "4.120.120 Assicurazione sugli infortuni scolastici": 1,
        "7.70.20 Protezione degli animali": 1,
        "5.20.30.10 Protezione dal fuoco, pompieri": 1
      }
    },
    "Ordinanza parlamentaria (decreto legislativo)": {
      "total": 4,
      "by_topic": {
        "A3.3 PROCEDURA AMMINISTRATIVA, CIVILE E PENALE": 1,
        "644 Esenzioni e alleggerimenti fiscali": 1,
        "73 Commesse e appalti pubblici": 1,
        "752 Trasporti pubblici": 1
      },
      "by_global_category": {
        "3.20.50 Assistenza giudiziaria": 1,
        "6.20.100 Esenzione e agevolazioni fiscali": 1,
        "7.30.40 Commesse pubbliche": 1
      }
    },
    "Ordinanza": {
      "total": 2,
      "by_topic": {
        "11 Stemma": 1,
        "835 Protezione dagli incendi": 1
      },
      "by_global_category": {
        "1.10.20 Colori e sigilli": 1,
        "5.20.30.20 Protezione dagli incendi": 1
      }
    },
    "Altro": {
      "total": 1,
      "by_topic": {
        "A5.3 UNIVERSITÀ, RICERCA E SCUOLE SUPERIORI": 1
      },
      "by_global_category": {
        "4.160 Scienza, ricerca": 1
      }
    }
  },
  "by_topic_tree": [
    {
      "identifier": "1",
      "title": "STATO - POPOLO - AUTORITÀ",
      "total": 1,
      "own": 0,
      "by_type": {
        "Ordinanza": 1
      },
      "children": [
        {
          "identifier": "11",
          "title": "Stemma",
          "total": 1,
          "own": 1,
          "by_type": {
            "Ordinanza": 1
          }
        }
      ]
    },
    {
      "identifier": "2",
      "title": "DIRITTO CIVILE",
      "total": 1,
      "own": 0,
      "by_type": {
        "Legge": 1
      },
      "children": [
        {
          "identifier": "21",
          "title": "Disposizioni di esecuzione del Codice civile",
          "total": 1,
          "own": 0,
          "by_type": {
            "Legge": 1
          },
          "children": [
            {
              "identifier": "215",
              "title": "Diritti reali",
              "total": 1,
              "own": 1,
              "by_type": {
                "Legge": 1
              }
            }
          ]
        }
      ]
    },
    {
      "identifier": "6",
      "title": "FINANZE",
      "total": 1,
      "own": 0,
      "by_type": {
        "Ordinanza parlamentaria (decreto legislativo)": 1
      },
      "children": [
        {
          "identifier": "64",
          "title": "Imposte",
          "total": 1,
          "own": 0,
          "by_type": {
            "Ordinanza parlamentaria (decreto legislativo)": 1
          },
          "children": [
            {
              "identifier": "644",
              "title": "Esenzioni e alleggerimenti fiscali",
              "total": 1,
              "own": 1,
              "by_type": {
                "Ordinanza parlamentaria (decreto legislativo)": 1
              }
            }
          ]
        }
      ]
    },
    {
      "identifier": "7",
      "title": "EDILIZIA - BENI PUBBLICI - ENERGIA - TRASPORTI",
      "total": 2,
      "own": 0,
      "by_type": {
        "Ordinanza parlamentaria (decreto legislativo)": 2
      },
      "children": [
        {
          "identifier": "73",
          "title": "Commesse e appalti pubblici",
          "total": 1,
          "own": 1,
          "by_type": {
            "Ordinanza parlamentaria (decreto legislativo)": 1
          }
        },
        {
          "identifier": "75",
          "title": "Mobilità",
          "total": 1,
          "own": 0,
          "by_type": {
            "Ordinanza parlamentaria (decreto legislativo)": 1
          },
          "children": [
            {
              "identifier": "752",
              "title": "Trasporti pubblici",
              "total": 1,
              "own": 1,
              "by_type": {
                "Ordinanza parlamentaria (decreto legislativo)": 1
              }
            }
          ]
        }
      ]
    },
    {
      "identifier": "8",
      "title": "SANITÀ - AMBIENTE - LAVORO - SICUREZZA SOCIALE",
      "total": 4,
      "own": 0,
      "by_type": {
        "Legge": 2,
        "Regolamento": 1,
        "Ordinanza": 1
      },
      "children": [
        {
          "identifier": "81",
          "title": "Ospedali, professioni sanitarie",
          "total": 1,
          "own": 0,
          "by_type": {
            "Regolamento": 1
          },
          "children": [
            {
              "identifier": "811",
              "title": "Stabilimenti ospedalieri",
              "total": 1,
              "own": 1,
              "by_type": {
                "Regolamento": 1
              }
            }
          ]
        },
        {
          "identifier": "82",
          "title": "Misure sanitarie",
          "total": 1,
          "own": 0,
          "by_type": {
            "Legge": 1
          },
          "children": [
            {
              "identifier": "824",
              "title": "Derrate alimentari e oggetti d’uso",
              "total": 1,
              "own": 1,
              "by_type": {
                "Legge": 1
              }
            }
          ]
        },
        {
          "identifier": "83",
          "title": "Protezione dell'ambiente",
          "total": 2,
          "own": 0,
          "by_type": {
            "Legge": 1,
            "Ordinanza": 1
          },
          "children": [
            {
              "identifier": "835",
              "title": "Protezione dagli incendi",
              "total": 2,
              "own": 2,
              "by_type": {
                "Legge": 1,
                "Ordinanza": 1
              }
            }
          ]
        }
      ]
    },
    {
      "identifier": "A",
      "title": "Atti abrogati della numerazione prima del luglio 2018",
      "total": 10,
      "own": 0,
      "by_type": {
        "Regolamento": 5,
        "Legge": 3,
        "Ordinanza parlamentaria (decreto legislativo)": 1,
        "Altro": 1
      },
      "children": [
        {
          "identifier": "A1",
          "title": "NORME GENERALI",
          "total": 2,
          "own": 0,
          "by_type": {
            "Regolamento": 1,
            "Legge": 1
          },
          "children": [
            {
              "identifier": "A1.4",
              "title": "ORDINE PUBBLICO",
              "total": 2,
              "own": 2,
              "by_type": {
                "Regolamento": 1,
                "Legge": 1
              }
            }
          ]
        },
        {
          "identifier": "A2",
          "title": "ORGANIZZAZIONE DEL CANTONE",
          "total": 1,
          "own": 0,
          "by_type": {
            "Regolamento": 1
          },
          "children": [
            {
              "identifier": "A2.5",
              "title": "AMMINISTRAZIONE CANTONALE",
              "total": 1,
              "own": 1,
              "by_type": {
                "Regolamento": 1
              }
            }
          ]
        },
        {
          "identifier": "A3",
          "title": "ORGANIZZAZIONE GIUDIZIARIA E PROCEDURA",
          "total": 1,
          "own": 0,
          "by_type": {
            "Ordinanza parlamentaria (decreto legislativo)": 1
          },
          "children": [
            {
              "identifier": "A3.3",
              "title": "PROCEDURA AMMINISTRATIVA, CIVILE E PENALE",
              "total": 1,
              "own": 1,
              "by_type": {
                "Ordinanza parlamentaria (decreto legislativo)": 1
              }
            }
          ]
        },
        {
          "identifier": "A5",
          "title": "ISTRUZIONE, CULTURA E TEMPO LIBERO",
          "total": 3,
          "own": 0,
          "by_type": {
            "Legge": 1,
            "Regolamento": 1,
            "Altro": 1
          },
          "children": [
            {
              "identifier": "A5.1",
              "title": "SCUOLA",
              "total": 2,
              "own": 2,
              "by_type": {
                "Legge": 1,
                "Regolamento": 1
              }
            },
            {
              "identifier": "A5.3",
              "title": "UNIVERSITÀ, RICERCA E SCUOLE SUPERIORI",
              "total": 1,
              "own": 1,
              "by_type": {
                "Altro": 1
              }
            }
          ]
        },
        {
          "identifier": "A8",
          "title": "ECONOMIA RURALE E FORESTALE, CACCIA E PESCA",
          "total": 2,
          "own": 0,
          "by_type": {
            "Regolamento": 1,
            "Legge": 1
          },
          "children": [
            {
              "identifier": "A8.1",
              "title": "AGRICOLTURA",
              "total": 1,
              "own": 1,
              "by_type": {
                "Regolamento": 1
              }
            },
            {
              "identifier": "A8.5",
              "title": "CACCIA E PESCA",
              "total": 1,
              "own": 1,
              "by_type": {
                "Legge": 1
              }
            }
          ]
        },
        {
          "identifier": "A11",
          "title": "COMMERCIO, INDUSTRIA, ARTI E MESTIERI, SVILUPPO ECONOMICO",
          "total": 1,
          "own": 0,
          "by_type": {
            "Regolamento": 1
          },
          "children": [
            {
              "identifier": "A11.3",
              "title": "SVILUPPO ECONOMICO E MISURE A FAVORE DEI SINGOLI RAMI ECONOMICI",
              "total": 1,
              "own": 1,
              "by_type": {
                "Regolamento": 1
              }
            }
          ]
        }
      ]
    }
  ],
  "by_global_category_tree": [
    {
      "identifier": "1",
      "title": "Staat",
      "total": 2,
      "own": 0,
      "by_type": {
        "Ordinanza": 1,
        "Regolamento": 1
      },
      "children": [
        {
          "identifier": "1.10",
          "title": "Grundlagen",
          "total": 1,
          "own": 0,
          "by_type": {
            "Ordinanza": 1
          },
          "children": [
            {
              "identifier": "1.10.20",
              "title": "Wappen",
              "total": 1,
              "own": 1,
              "by_type": {
                "Ordinanza": 1
              }
            }
          ]
        },
        {
          "identifier": "1.20",
          "title": "Behörden",
          "total": 1,
          "own": 0,
          "by_type": {
            "Regolamento": 1
          },
          "children": [
            {
              "identifier": "1.20.20",
              "title": "Regierung und Verwaltung",
              "total": 1,
              "own": 0,
              "by_type": {
                "Regolamento": 1
              },
              "children": [
                {
                  "identifier": "1.20.20.40",
                  "title": "Personalrecht",
                  "total": 1,
                  "own": 0,
                  "by_type": {
                    "Regolamento": 1
                  },
                  "children": [
                    {
                      "identifier": "1.20.20.40.50",
                      "title": "Renten, Versicherungsansprüche",
                      "total": 1,
                      "own": 1,
                      "by_type": {
                        "Regolamento": 1
                      }
                    }
                  ]
                }
              ]
            }
          ]
        }
      ]
    },
    {
      "identifier": "2",
      "title": "Zivilrecht",
      "total": 2,
      "own": 0,
      "by_type": {
        "Legge": 1,
        "Regolamento": 1
      },
      "children": [
        {
          "identifier": "2.10",
          "title": "Einführungsgesetzgebung zum ZGB",
          "total": 1,
          "own": 0,
          "by_type": {
            "Legge": 1
          },
          "children": [
            {
              "identifier": "2.10.40",
              "title": "Sachenrecht",
              "total": 1,
              "own": 0,
              "by_type": {
                "Legge": 1
              },
              "children": [
                {
                  "identifier": "2.10.40.10",
                  "title": "Schätzung von Grundstücken",
                  "total": 1,
                  "own": 1,
                  "by_type": {
                    "Legge": 1
                  }
                }
              ]
            }
          ]
        },
        {
          "identifier": "2.20",
          "title": "Einführungsgesetzgebung OR",
          "total": 1,
          "own": 0,
          "by_type": {
            "Regolamento": 1
          },
          "children": [
            {
              "identifier": "2.20.10",
              "title": "Vertragsverhältnisse",
              "total": 1,
              "own": 0,
              "by_type": {
                "Regolamento": 1
              },
              "children": [
                {
                  "identifier": "2.20.10.20",
                  "title": "Miete und Pacht",
                  "total": 1,
                  "own": 0,
                  "by_type": {
                    "Regolamento": 1
                  },
                  "children": [
                    {
                      "identifier": "2.20.10.20.10",
                      "title": "Landwirtschaftliche Pacht",
                      "total": 1,
                      "own": 1,
                      "by_type": {
                        "Regolamento": 1
                      }
                    }
                  ]
                }
              ]
            }
          ]
        }
      ]
    },
    {
      "identifier": "3",
      "title": "Strafrecht",
      "total": 1,
      "own": 0,
      "by_type": {
        "Ordinanza parlamentaria (decreto legislativo)": 1
      },
      "children": [
        {
          "identifier": "3.20",
          "title": "Strafprozess",
          "total": 1,
          "own": 0,
          "by_type": {
            "Ordinanza parlamentaria (decreto legislativo)": 1
          },
          "children": [
            {
              "identifier": "3.20.50",
              "title": "Rechtshilfe",
              "total": 1,
              "own": 1,
              "by_type": {
                "Ordinanza parlamentaria (decreto legislativo)": 1
              }
            }
          ]
        }
      ]
    },
    {
      "identifier": "4",
      "title": "Schulwesen, Wissenschaft, Dokumentation und Kultur",
      "total": 3,
      "own": 0,
      "by_type": {
        "Legge": 1,
        "Regolamento": 1,
        "Altro": 1
      },
      "children": [
        {
          "identifier": "4.120",
          "title": "Qualitätssicherung, Aufsicht, Leitung",
          "total": 1,
          "own": 0,
          "by_type": {
            "Legge": 1
          },
          "children": [
            {
              "identifier": "4.120.120",
              "title": "Schulversicherung",
              "total": 1,
              "own": 1,
              "by_type": {
                "Legge": 1
              }
            }
          ]
        },
        {
          "identifier": "4.140",
          "title": "Anerkennung von Diplomen",
          "total": 1,
          "own": 1,
          "by_type": {
            "Regolamento": 1
          }
        },
        {
          "identifier": "4.160",
          "title": "Wissenschaft, Forschung",
          "total": 1,
          "own": 1,
          "by_type": {
            "Altro": 1
          }
        }
      ]
    },
    {
      "identifier": "5",
      "title": "Verteidigung, Bevölkerungsschutz, Polizeiwesen",
      "total": 2,
      "own": 0,
      "by_type": {
        "Legge": 1,
        "Ordinanza": 1
      },
      "children": [
        {
          "identifier": "5.20",
          "title": "Bevölkerungsschutz",
          "total": 2,
          "own": 0,
          "by_type": {
            "Legge": 1,
            "Ordinanza": 1
          },
          "children": [
            {
              "identifier": "5.20.30",
              "title": "Feuerwehr / Elementarschäden",
              "total": 2,
              "own": 0,
              "by_type": {
                "Legge": 1,
                "Ordinanza": 1
              },
              "children": [
                {
                  "identifier": "5.20.30.10",
                  "title": "Feuerwehr",
                  "total": 1,
                  "own": 1,
                  "by_type": {
                    "Legge": 1
                  }
                },
                {
                  "identifier": "5.20.30.20",
                  "title": "Brandschutz",
                  "total": 1,
                  "own": 1,
                  "by_type": {
                    "Ordinanza": 1
                  }
                }
              ]
            }
          ]
        }
      ]
    },
    {
      "identifier": "6",
      "title": "Finanzen, Steuern, Monopole, Staatliche Unternehmen",
      "total": 1,
      "own": 0,
      "by_type": {
        "Ordinanza parlamentaria (decreto legislativo)": 1
      },
      "children": [
        {
          "identifier": "6.20",
          "title": "Steuern",
          "total": 1,
          "own": 0,
          "by_type": {
            "Ordinanza parlamentaria (decreto legislativo)": 1
          },
          "children": [
            {
              "identifier": "6.20.100",
              "title": "Steuerbefreiung und -erleichterungen",
              "total": 1,
              "own": 1,
              "by_type": {
                "Ordinanza parlamentaria (decreto legislativo)": 1
              }
            }
          ]
        }
      ]
    },
    {
      "identifier": "7",
      "title": "Raumplanungs- und Baurecht, Enteignung, Öffentliche Werke, Energie, Verkehr, Umweltschutz, Naturschutz",
      "total": 2,
      "own": 0,
      "by_type": {
        "Ordinanza parlamentaria (decreto legislativo)": 1,
        "Legge": 1
      },
      "children": [
        {
          "identifier": "7.30",
          "title": "Öffentliche Werke",
          "total": 1,
          "own": 0,
          "by_type": {
            "Ordinanza parlamentaria (decreto legislativo)": 1
          },
          "children": [
            {
              "identifier": "7.30.40",
              "title": "Submission",
              "total": 1,
              "own": 1,
              "by_type": {
                "Ordinanza parlamentaria (decreto legislativo)": 1
              }
            }
          ]
        },
        {
          "identifier": "7.70",
          "title": "Natur- und Heimatschutz",
          "total": 1,
          "own": 0,
          "by_type": {
            "Legge": 1
          },
          "children": [
            {
              "identifier": "7.70.20",
              "title": "Tierschutz",
              "total": 1,
              "own": 1,
              "by_type": {
                "Legge": 1
              }
            }
          ]
        }
      ]
    },
    {
      "identifier": "9",
      "title": "Wirtschaft",
      "total": 1,
      "own": 0,
      "by_type": {
        "Regolamento": 1
      },
      "children": [
        {
          "identifier": "9.50",
          "title": "Gewerbe",
          "total": 1,
          "own": 0,
          "by_type": {
            "Regolamento": 1
          },
          "children": [
            {
              "identifier": "9.50.10",
              "title": "Dienstleistungen",
              "total": 1,
              "own": 0,
              "by_type": {
                "Regolamento": 1
              },
              "children": [
                {
                  "identifier": "9.50.10.10",
                  "title": "Berufsausübungsbewilligungen",
                  "total": 1,
                  "own": 1,
                  "by_type": {
                    "Regolamento": 1
                  }
                }
              ]
            }
          ]
        }
      ]
    }
  ],
  "languages_available": {
    "it": 19
  }
}