{
  "date_prefix": "1825",
  "count": 2,
  "publications": [
    {
      "date": "1825-12-12",
      "sr_number": "250.3",
      "title": "Übereinkunft",
      "scope": "cantonal",
      "language": "de",
      "canton": "OW",
      "path": "ch/ow/de/250.3.md",
      "url_main": "https://raw.githubusercontent.com/swiss-law-as-source/swiss-law-as-source.github.io/main/ch/ow/de/250.3.md",
      "systematic_category": "250 Schuldbetreibung und Konkurs",
      "category_type": "Staatsvertrag"
    },
    {
      "date": "1825-12-12",
      "sr_number": "280.94",
      "title": "Entrée en vigueur dès le 13.05.1826 (Actuelle)",
      "scope": "cantonal",
      "language": "fr",
      "canton": "VD",
      "path": "ch/vd/fr/280.94.md",
      "url_main": "https://raw.githubusercontent.com/swiss-law-as-source/swiss-law-as-source.github.io/main/ch/vd/fr/280.94.md",
      "systematic_category": "280.900 Conventions (poursuite et faillite)",
      "category_type": "Traité international"
    }
  ]
}