{
  "date_prefix": "1930",
  "count": 53,
  "publications": [
    {
      "date": "1930-01-01",
      "sr_number": "0.274.181.368",
      "title": "Notenaustausch vom 24. Dezember 1929 zwischen der Schweiz und Deutschland über die Vollstreckbarerklärung von Kostenentscheidungen",
      "scope": "federal",
      "language": "de",
      "canton": "",
      "path": "ch/0/de/0.274.181.368.md",
      "url_main": "https://raw.githubusercontent.com/swiss-law-as-source/swiss-law-as-source.github.io/main/ch/0/de/0.274.181.368.md"
    },
    {
      "date": "1930-01-01",
      "sr_number": "0.274.181.368",
      "title": "Échange de notes du 24 décembre 1929 entre la Suisse et l'Allemagne concernant l'exequatur des décisions relatives aux frais et dépens du procès",
      "scope": "federal",
      "language": "fr",
      "canton": "",
      "path": "ch/0/fr/0.274.181.368.md",
      "url_main": "https://raw.githubusercontent.com/swiss-law-as-source/swiss-law-as-source.github.io/main/ch/0/fr/0.274.181.368.md"
    },
    {
      "date": "1930-01-01",
      "sr_number": "0.274.181.368",
      "title": "Scambio di note del 24 dicembre 1929 fra la Svizzera e la Germania concernente la dichiarazione di esecutività delle decisioni giudiziarie relative alle spese",
      "scope": "federal",
      "language": "it",
      "canton": "",
      "path": "ch/0/it/0.274.181.368.md",
      "url_main": "https://raw.githubusercontent.com/swiss-law-as-source/swiss-law-as-source.github.io/main/ch/0/it/0.274.181.368.md"
    },
    {
      "date": "1930-01-01",
      "sr_number": "172.216.3",
      "title": "Bundesbeschluss vom 8. Oktober 1920 über die Errichtung des Eidgenössischen Arbeitsamtes ",
      "scope": "federal",
      "language": "de",
      "canton": "",
      "path": "ch/172/de/172.216.3.md",
      "url_main": "https://raw.githubusercontent.com/swiss-law-as-source/swiss-law-as-source.github.io/main/ch/172/de/172.216.3.md"
    },
    {
      "date": "1930-01-01",
      "sr_number": "172.216.3",
      "title": "Arrêté fédéral du 8 octobre 1920 portant création de l'office fédéral du travail ",
      "scope": "federal",
      "language": "fr",
      "canton": "",
      "path": "ch/172/fr/172.216.3.md",
      "url_main": "https://raw.githubusercontent.com/swiss-law-as-source/swiss-law-as-source.github.io/main/ch/172/fr/172.216.3.md"
    },
    {
      "date": "1930-01-01",
      "sr_number": "172.216.3",
      "title": "Decreto federale dell'8 ottobre 1920 che istituisce l'Ufficio federale del lavoro ",
      "scope": "federal",
      "language": "it",
      "canton": "",
      "path": "ch/172/it/172.216.3.md",
      "url_main": "https://raw.githubusercontent.com/swiss-law-as-source/swiss-law-as-source.github.io/main/ch/172/it/172.216.3.md"
    },
    {
      "date": "1930-01-01",
      "sr_number": "172.216.31",
      "title": "Bundesbeschluss vom 21. Juni 1929 über die Vereinigung der Abteilung für Industrie und Gewerbe und des eidgenössischen Arbeitsamtes ",
      "scope": "federal",
      "language": "de",
      "canton": "",
      "path": "ch/172/de/172.216.31.md",
      "url_main": "https://raw.githubusercontent.com/swiss-law-as-source/swiss-law-as-source.github.io/main/ch/172/de/172.216.31.md"
    },
    {
      "date": "1930-01-01",
      "sr_number": "172.216.31",
      "title": "Arrêté fédéral du 21 juin 1929 portant fusion de la Division de l'industrie et des arts et métiers et de l'office fédéral du travail",
      "scope": "federal",
      "language": "fr",
      "canton": "",
      "path": "ch/172/fr/172.216.31.md",
      "url_main": "https://raw.githubusercontent.com/swiss-law-as-source/swiss-law-as-source.github.io/main/ch/172/fr/172.216.31.md"
    },
    {
      "date": "1930-01-01",
      "sr_number": "172.216.31",
      "title": "Decreto federale del 21 giugno 1929 che riunisce in un solo ufficio la Divisione dell'industria e delle arti e mestieri e l'Ufficio del lavoro",
      "scope": "federal",
      "language": "it",
      "canton": "",
      "path": "ch/172/it/172.216.31.md",
      "url_main": "https://raw.githubusercontent.com/swiss-law-as-source/swiss-law-as-source.github.io/main/ch/172/it/172.216.31.md"
    },
    {
      "date": "1930-02-01",
      "sr_number": "935.52",
      "title": "Bundesgesetz vom 5. Oktober 1929 über die Spielbanken ",
      "scope": "federal",
      "language": "de",
      "canton": "",
      "path": "ch/935/de/935.52.md",
      "url_main": "https://raw.githubusercontent.com/swiss-law-as-source/swiss-law-as-source.github.io/main/ch/935/de/935.52.md"
    },
    {
      "date": "1930-02-01",
      "sr_number": "935.52",
      "title": "Loi fédérale du 5 octobre 1929 sur les maisons de jeu",
      "scope": "federal",
      "language": "fr",
      "canton": "",
      "path": "ch/935/fr/935.52.md",
      "url_main": "https://raw.githubusercontent.com/swiss-law-as-source/swiss-law-as-source.github.io/main/ch/935/fr/935.52.md"
    },
    {
      "date": "1930-02-01",
      "sr_number": "935.52",
      "title": "Legge federale del 5 ottobre 1929 sulle case da giuoco",
      "scope": "federal",
      "language": "it",
      "canton": "",
      "path": "ch/935/it/935.52.md",
      "url_main": "https://raw.githubusercontent.com/swiss-law-as-source/swiss-law-as-source.github.io/main/ch/935/it/935.52.md"
    },
    {
      "date": "1930-02-01",
      "sr_number": "935.52",
      "title": "Bundesgesetz vom 5. Oktober 1929 über die Spielbanken ",
      "scope": "federal",
      "language": "de",
      "canton": "",
      "path": "ch/935/de/935.52.md",
      "url_main": "https://raw.githubusercontent.com/swiss-law-as-source/swiss-law-as-source.github.io/main/ch/935/de/935.52.md"
    },
    {
      "date": "1930-02-01",
      "sr_number": "935.52",
      "title": "Loi fédérale du 5 octobre 1929 sur les maisons de jeu",
      "scope": "federal",
      "language": "fr",
      "canton": "",
      "path": "ch/935/fr/935.52.md",
      "url_main": "https://raw.githubusercontent.com/swiss-law-as-source/swiss-law-as-source.github.io/main/ch/935/fr/935.52.md"
    },
    {
      "date": "1930-02-01",
      "sr_number": "935.52",
      "title": "Legge federale del 5 ottobre 1929 sulle case da giuoco",
      "scope": "federal",
      "language": "it",
      "canton": "",
      "path": "ch/935/it/935.52.md",
      "url_main": "https://raw.githubusercontent.com/swiss-law-as-source/swiss-law-as-source.github.io/main/ch/935/it/935.52.md"
    },
    {
      "date": "1930-03-03",
      "sr_number": "0.142.111.231",
      "title": "Niederlassungs- und Handelsabkommen vom 10. Juni 1929 zwischen der Schweiz und Albanien (mit Schlussprotokoll)",
      "scope": "federal",
      "language": "de",
      "canton": "",
      "path": "ch/0/de/0.142.111.231.md",
      "url_main": "https://raw.githubusercontent.com/swiss-law-as-source/swiss-law-as-source.github.io/main/ch/0/de/0.142.111.231.md"
    },
    {
      "date": "1930-03-03",
      "sr_number": "0.142.111.231",
      "title": "Convention d'établissement et de commerce du 10 juin 1929 entre la Suisse et l'Albanie (avec prot. fin.)",
      "scope": "federal",
      "language": "fr",
      "canton": "",
      "path": "ch/0/fr/0.142.111.231.md",
      "url_main": "https://raw.githubusercontent.com/swiss-law-as-source/swiss-law-as-source.github.io/main/ch/0/fr/0.142.111.231.md"
    },
    {
      "date": "1930-03-03",
      "sr_number": "0.142.111.231",
      "title": "Convenzione di domicilio e di commercio del 10 giugno 1929 tra la Svizzera e l'Albania (con Protocollo finale)",
      "scope": "federal",
      "language": "it",
      "canton": "",
      "path": "ch/0/it/0.142.111.231.md",
      "url_main": "https://raw.githubusercontent.com/swiss-law-as-source/swiss-law-as-source.github.io/main/ch/0/it/0.142.111.231.md"
    },
    {
      "date": "1930-04-19",
      "sr_number": "0.946.293.211",
      "title": "Provisorisches Handelsabkommen vom 19. April 1930 zwischen der Schweiz und Ägypten",
      "scope": "federal",
      "language": "de",
      "canton": "",
      "path": "ch/0/de/0.946.293.211.md",
      "url_main": "https://raw.githubusercontent.com/swiss-law-as-source/swiss-law-as-source.github.io/main/ch/0/de/0.946.293.211.md"
    },
    {
      "date": "1930-04-19",
      "sr_number": "0.946.293.211",
      "title": "Arrangement commercial provisoire du 19 avril 1930 entre la Suisse et l'Égypte",
      "scope": "federal",
      "language": "fr",
      "canton": "",
      "path": "ch/0/fr/0.946.293.211.md",
      "url_main": "https://raw.githubusercontent.com/swiss-law-as-source/swiss-law-as-source.github.io/main/ch/0/fr/0.946.293.211.md"
    },
    {
      "date": "1930-04-19",
      "sr_number": "0.946.293.211",
      "title": "Accordo commerciale provvisorio del 19 aprile 1930 tra la Svizzera e l'Egitto",
      "scope": "federal",
      "language": "it",
      "canton": "",
      "path": "ch/0/it/0.946.293.211.md",
      "url_main": "https://raw.githubusercontent.com/swiss-law-as-source/swiss-law-as-source.github.io/main/ch/0/it/0.946.293.211.md"
    },
    {
      "date": "1930-06-07",
      "sr_number": "0.193.417.41",
      "title": "Vertrag vom 20. September 1929 zwischen der Schweiz und der Tschechoslowakei zur Erledigung von Streitigkeiten im Vergleichs-, Gerichts- und Schiedsverfahren",
      "scope": "federal",
      "language": "de",
      "canton": "",
      "path": "ch/0/de/0.193.417.41.md",
      "url_main": "https://raw.githubusercontent.com/swiss-law-as-source/swiss-law-as-source.github.io/main/ch/0/de/0.193.417.41.md"
    },
    {
      "date": "1930-06-07",
      "sr_number": "0.193.417.41",
      "title": "Traité de conciliation, de règlement judiciaire et d'arbitrage du 20 septembre 1929 entre la Suisse et la Tchécoslovaquie",
      "scope": "federal",
      "language": "fr",
      "canton": "",
      "path": "ch/0/fr/0.193.417.41.md",
      "url_main": "https://raw.githubusercontent.com/swiss-law-as-source/swiss-law-as-source.github.io/main/ch/0/fr/0.193.417.41.md"
    },
    {
      "date": "1930-06-07",
      "sr_number": "0.193.417.41",
      "title": "Trattato di conciliazione, di regolamento giudiziario e di arbitrato del 20 settembre 1929 tra la Svizzera e la Cecoslovacchia",
      "scope": "federal",
      "language": "it",
      "canton": "",
      "path": "ch/0/it/0.193.417.41.md",
      "url_main": "https://raw.githubusercontent.com/swiss-law-as-source/swiss-law-as-source.github.io/main/ch/0/it/0.193.417.41.md"
    },
    {
      "date": "1930-06-07",
      "sr_number": "0.221.554.4",
      "title": "Schlussakte der Genfer Konferenz zur Vereinheitlichung des Wechselrechts vom 7. Juni 1930",
      "scope": "federal",
      "language": "de",
      "canton": "",
      "path": "ch/0/de/0.221.554.4.md",
      "url_main": "https://raw.githubusercontent.com/swiss-law-as-source/swiss-law-as-source.github.io/main/ch/0/de/0.221.554.4.md"
    },
    {
      "date": "1930-06-07",
      "sr_number": "0.221.554.4",
      "title": "Acte final de la Conférence de Genève pour l'unification du droit en matière de lettres de change et de billets à ordre, du 7 juin 1930",
      "scope": "federal",
      "language": "fr",
      "canton": "",
      "path": "ch/0/fr/0.221.554.4.md",
      "url_main": "https://raw.githubusercontent.com/swiss-law-as-source/swiss-law-as-source.github.io/main/ch/0/fr/0.221.554.4.md"
    },
    {
      "date": "1930-06-07",
      "sr_number": "0.221.554.4",
      "title": "Atto finale della Conferenza di Ginevra per l'unificazione del diritto in materia di cambiali e di vaglia cambiari, del 7 giugno 1930",
      "scope": "federal",
      "language": "it",
      "canton": "",
      "path": "ch/0/it/0.221.554.4.md",
      "url_main": "https://raw.githubusercontent.com/swiss-law-as-source/swiss-law-as-source.github.io/main/ch/0/it/0.221.554.4.md"
    },
    {
      "date": "1930-06-07",
      "sr_number": "0.747.224.052.1",
      "title": "Vertrag vom 28. März 1929 zwischen der Schweiz und Deutschland über die Regulierung des Rheins zwischen Strassburg/Kehl und Istein",
      "scope": "federal",
      "language": "de",
      "canton": "",
      "path": "ch/0/de/0.747.224.052.1.md",
      "url_main": "https://raw.githubusercontent.com/swiss-law-as-source/swiss-law-as-source.github.io/main/ch/0/de/0.747.224.052.1.md"
    },
    {
      "date": "1930-06-07",
      "sr_number": "0.747.224.052.1",
      "title": "Convention du 28 mars 1929 entre la Suisse et l'Allemagne sur la régularisation du Rhin entre Strasbourg-Kehl et Istein",
      "scope": "federal",
      "language": "fr",
      "canton": "",
      "path": "ch/0/fr/0.747.224.052.1.md",
      "url_main": "https://raw.githubusercontent.com/swiss-law-as-source/swiss-law-as-source.github.io/main/ch/0/fr/0.747.224.052.1.md"
    },
    {
      "date": "1930-06-07",
      "sr_number": "0.747.224.052.1",
      "title": "Convenzione del 28 marzo 1929 tra la Svizzera e la Germania sulla sistemazione del Reno tra Strasburgo/Kehl ed Istein",
      "scope": "federal",
      "language": "it",
      "canton": "",
      "path": "ch/0/it/0.747.224.052.1.md",
      "url_main": "https://raw.githubusercontent.com/swiss-law-as-source/swiss-law-as-source.github.io/main/ch/0/it/0.747.224.052.1.md"
    },
    {
      "date": "1930-08-07",
      "sr_number": "0.193.417.63",
      "title": "Vertrag vom 9. Dezember 1928 zwischen der Schweiz und der Türkei zur Erledigung von Streitigkeiten im Vergleichs-, Gerichts- und Schiedsverfahren",
      "scope": "federal",
      "language": "de",
      "canton": "",
      "path": "ch/0/de/0.193.417.63.md",
      "url_main": "https://raw.githubusercontent.com/swiss-law-as-source/swiss-law-as-source.github.io/main/ch/0/de/0.193.417.63.md"
    },
    {
      "date": "1930-08-07",
      "sr_number": "0.193.417.63",
      "title": "Traité de conciliation, de règlement judiciaire et d'arbitrage du 9 décembre 1928 entre la Suisse et la Turquie",
      "scope": "federal",
      "language": "fr",
      "canton": "",
      "path": "ch/0/fr/0.193.417.63.md",
      "url_main": "https://raw.githubusercontent.com/swiss-law-as-source/swiss-law-as-source.github.io/main/ch/0/fr/0.193.417.63.md"
    },
    {
      "date": "1930-08-07",
      "sr_number": "0.193.417.63",
      "title": "Trattato di conciliazione, di regolamento giudiziario e di arbitrato del 9 dicembre 1928 tra la Svizzera e la Turchia",
      "scope": "federal",
      "language": "it",
      "canton": "",
      "path": "ch/0/it/0.193.417.63.md",
      "url_main": "https://raw.githubusercontent.com/swiss-law-as-source/swiss-law-as-source.github.io/main/ch/0/it/0.193.417.63.md"
    },
    {
      "date": "1930-09-06",
      "sr_number": "865.51",
      "title": "Beschluss betreffend den eidgenössischen Buss- und Bettag",
      "scope": "cantonal",
      "language": "de",
      "canton": "FR",
      "path": "ch/fr/de/865.51.md",
      "url_main": "https://raw.githubusercontent.com/swiss-law-as-source/swiss-law-as-source.github.io/main/ch/fr/de/865.51.md"
    },
    {
      "date": "1930-09-06",
      "sr_number": "865.51",
      "title": "Arrêté concernant la célébration de la Fête fédérale d'actions de grâces",
      "scope": "cantonal",
      "language": "fr",
      "canton": "FR",
      "path": "ch/fr/fr/865.51.md",
      "url_main": "https://raw.githubusercontent.com/swiss-law-as-source/swiss-law-as-source.github.io/main/ch/fr/fr/865.51.md",
      "systematic_category": "865 Feiertage",
      "global_category": "8.20.10.30 Sonn- und Feiertage",
      "category_type": "Anderes"
    },
    {
      "date": "1930-09-15",
      "sr_number": "0.193.415.18",
      "title": "Vertrag vom 16. September 1929 zwischen der Schweiz und Luxemburg zur Erledigung von Streitigkeiten im Vergleichs-, Gerichts- und Schiedsverfahren",
      "scope": "federal",
      "language": "de",
      "canton": "",
      "path": "ch/0/de/0.193.415.18.md",
      "url_main": "https://raw.githubusercontent.com/swiss-law-as-source/swiss-law-as-source.github.io/main/ch/0/de/0.193.415.18.md"
    },
    {
      "date": "1930-09-15",
      "sr_number": "0.193.415.18",
      "title": "Traité de conciliation, de règlement judiciaire et d'arbitrage du 16 septembre 1929 entre la Suisse et le Luxembourg",
      "scope": "federal",
      "language": "fr",
      "canton": "",
      "path": "ch/0/fr/0.193.415.18.md",
      "url_main": "https://raw.githubusercontent.com/swiss-law-as-source/swiss-law-as-source.github.io/main/ch/0/fr/0.193.415.18.md"
    },
    {
      "date": "1930-09-15",
      "sr_number": "0.193.415.18",
      "title": "Trattato di conciliazione, di regolamento giudiziario e di arbitrato del 16 settembre 1929 tra la Svizzera e il Lussemburgo",
      "scope": "federal",
      "language": "it",
      "canton": "",
      "path": "ch/0/it/0.193.415.18.md",
      "url_main": "https://raw.githubusercontent.com/swiss-law-as-source/swiss-law-as-source.github.io/main/ch/0/it/0.193.415.18.md"
    },
    {
      "date": "1930-10-01",
      "sr_number": "510.33",
      "title": "Verordnung vom 13. September 1930 über den Verkehr mit Betäubungsmitteln in der Armee",
      "scope": "federal",
      "language": "de",
      "canton": "",
      "path": "ch/510/de/510.33.md",
      "url_main": "https://raw.githubusercontent.com/swiss-law-as-source/swiss-law-as-source.github.io/main/ch/510/de/510.33.md"
    },
    {
      "date": "1930-10-01",
      "sr_number": "510.33",
      "title": "Ordonnance du 13 septembre 1930 concernant la police des stupéfiants dans l'armée",
      "scope": "federal",
      "language": "fr",
      "canton": "",
      "path": "ch/510/fr/510.33.md",
      "url_main": "https://raw.githubusercontent.com/swiss-law-as-source/swiss-law-as-source.github.io/main/ch/510/fr/510.33.md"
    },
    {
      "date": "1930-10-01",
      "sr_number": "510.33",
      "title": "Ordinanza del 13 settembre 1930 concernente la polizia degli stupefacenti nell'armata",
      "scope": "federal",
      "language": "it",
      "canton": "",
      "path": "ch/510/it/510.33.md",
      "url_main": "https://raw.githubusercontent.com/swiss-law-as-source/swiss-law-as-source.github.io/main/ch/510/it/510.33.md"
    },
    {
      "date": "1930-10-01",
      "sr_number": "510.33",
      "title": "Verordnung vom 13. September 1930 über den Verkehr mit Betäubungsmitteln in der Armee",
      "scope": "federal",
      "language": "de",
      "canton": "",
      "path": "ch/510/de/510.33.md",
      "url_main": "https://raw.githubusercontent.com/swiss-law-as-source/swiss-law-as-source.github.io/main/ch/510/de/510.33.md"
    },
    {
      "date": "1930-10-01",
      "sr_number": "510.33",
      "title": "Ordonnance du 13 septembre 1930 concernant la police des stupéfiants dans l'armée",
      "scope": "federal",
      "language": "fr",
      "canton": "",
      "path": "ch/510/fr/510.33.md",
      "url_main": "https://raw.githubusercontent.com/swiss-law-as-source/swiss-law-as-source.github.io/main/ch/510/fr/510.33.md"
    },
    {
      "date": "1930-10-01",
      "sr_number": "510.33",
      "title": "Ordinanza del 13 settembre 1930 concernente la polizia degli stupefacenti nell'armata",
      "scope": "federal",
      "language": "it",
      "canton": "",
      "path": "ch/510/it/510.33.md",
      "url_main": "https://raw.githubusercontent.com/swiss-law-as-source/swiss-law-as-source.github.io/main/ch/510/it/510.33.md"
    },
    {
      "date": "1930-10-08",
      "sr_number": "951.19",
      "title": "Bundesbeschluss vom 26. Juni 1930 über die Beteiligung der Schweizerischen Nationalbank an der Bank für Internationalen Zahlungsausgleich ",
      "scope": "federal",
      "language": "de",
      "canton": "",
      "path": "ch/951/de/951.19.md",
      "url_main": "https://raw.githubusercontent.com/swiss-law-as-source/swiss-law-as-source.github.io/main/ch/951/de/951.19.md"
    },
    {
      "date": "1930-10-08",
      "sr_number": "951.19",
      "title": "Arrêté fédéral du 26 juin 1930 sur la participation de la Banque nationale suisse à la Banque des règlements internationaux ",
      "scope": "federal",
      "language": "fr",
      "canton": "",
      "path": "ch/951/fr/951.19.md",
      "url_main": "https://raw.githubusercontent.com/swiss-law-as-source/swiss-law-as-source.github.io/main/ch/951/fr/951.19.md"
    },
    {
      "date": "1930-10-08",
      "sr_number": "951.19",
      "title": "Decreto federale del 26 giugno 1930 sulla partecipazione della Banca nazionale svizzera alla Banca dei pagamenti internazionali ",
      "scope": "federal",
      "language": "it",
      "canton": "",
      "path": "ch/951/it/951.19.md",
      "url_main": "https://raw.githubusercontent.com/swiss-law-as-source/swiss-law-as-source.github.io/main/ch/951/it/951.19.md"
    },
    {
      "date": "1930-10-08",
      "sr_number": "951.19",
      "title": "Bundesbeschluss vom 26. Juni 1930 über die Beteiligung der Schweizerischen Nationalbank an der Bank für Internationalen Zahlungsausgleich ",
      "scope": "federal",
      "language": "de",
      "canton": "",
      "path": "ch/951/de/951.19.md",
      "url_main": "https://raw.githubusercontent.com/swiss-law-as-source/swiss-law-as-source.github.io/main/ch/951/de/951.19.md"
    },
    {
      "date": "1930-10-08",
      "sr_number": "951.19",
      "title": "Arrêté fédéral du 26 juin 1930 sur la participation de la Banque nationale suisse à la Banque des règlements internationaux ",
      "scope": "federal",
      "language": "fr",
      "canton": "",
      "path": "ch/951/fr/951.19.md",
      "url_main": "https://raw.githubusercontent.com/swiss-law-as-source/swiss-law-as-source.github.io/main/ch/951/fr/951.19.md"
    },
    {
      "date": "1930-10-08",
      "sr_number": "951.19",
      "title": "Decreto federale del 26 giugno 1930 sulla partecipazione della Banca nazionale svizzera alla Banca dei pagamenti internazionali ",
      "scope": "federal",
      "language": "it",
      "canton": "",
      "path": "ch/951/it/951.19.md",
      "url_main": "https://raw.githubusercontent.com/swiss-law-as-source/swiss-law-as-source.github.io/main/ch/951/it/951.19.md"
    },
    {
      "date": "1930-12-29",
      "sr_number": "0.193.412.63",
      "title": "Vertrag vom 20. August 1927 zwischen der Schweiz und Kolumbien zur Erledigung von Streitigkeiten im Vergleichs-, Gerichts- und Schiedsverfahren",
      "scope": "federal",
      "language": "de",
      "canton": "",
      "path": "ch/0/de/0.193.412.63.md",
      "url_main": "https://raw.githubusercontent.com/swiss-law-as-source/swiss-law-as-source.github.io/main/ch/0/de/0.193.412.63.md"
    },
    {
      "date": "1930-12-29",
      "sr_number": "0.193.412.63",
      "title": "Traité de conciliation, de règlement judiciaire et d'arbitrage du 20 août 1927 entre la Suisse et la Colombie",
      "scope": "federal",
      "language": "fr",
      "canton": "",
      "path": "ch/0/fr/0.193.412.63.md",
      "url_main": "https://raw.githubusercontent.com/swiss-law-as-source/swiss-law-as-source.github.io/main/ch/0/fr/0.193.412.63.md"
    },
    {
      "date": "1930-12-29",
      "sr_number": "0.193.412.63",
      "title": "Trattato di conciliazione, di regolamento giudiziario e di arbitrato del 20 agosto 1927 tra la Svizzera e la Colombia",
      "scope": "federal",
      "language": "it",
      "canton": "",
      "path": "ch/0/it/0.193.412.63.md",
      "url_main": "https://raw.githubusercontent.com/swiss-law-as-source/swiss-law-as-source.github.io/main/ch/0/it/0.193.412.63.md"
    }
  ]
}