{
  "year": "1865",
  "entity": "VD",
  "total": 1,
  "categorized": 1,
  "uncategorized": 0,
  "by_type": {
    "Ordonnance parlementaire (décret)": {
      "total": 1,
      "by_topic": {
        "180.900 Conventions (Église)": 1
      },
      "by_global_category": {}
    }
  },
  "by_topic_tree": [
    {
      "identifier": "1",
      "title": "ÉTAT - PEUPLE - AUTORITÉS",
      "total": 1,
      "own": 0,
      "by_type": {
        "Ordonnance parlementaire (décret)": 1
      },
      "children": [
        {
          "identifier": "18",
          "title": "ÉGLISE, RELIGION",
          "total": 1,
          "own": 0,
          "by_type": {
            "Ordonnance parlementaire (décret)": 1
          },
          "children": [
            {
              "identifier": "180",
              "title": "Église",
              "total": 1,
              "own": 0,
              "by_type": {
                "Ordonnance parlementaire (décret)": 1
              },
              "children": [
                {
                  "identifier": "180.900",
                  "title": "Conventions (Église)",
                  "total": 1,
                  "own": 1,
                  "by_type": {
                    "Ordonnance parlementaire (décret)": 1
                  }
                }
              ]
            }
          ]
        }
      ]
    }
  ],
  "by_global_category_tree": [],
  "languages_available": {
    "fr": 1
  }
}