{
  "year": "1964",
  "entity": "VS",
  "total": 4,
  "categorized": 4,
  "uncategorized": 0,
  "by_type": {
    "Anderes": {
      "total": 4,
      "by_topic": {
        "53 Kriegswirtschaft": 2,
        "814 Umweltschutz": 2
      },
      "by_global_category": {
        "5.20.20 Landesversorgung": 2,
        "7.60.20 Gewässerschutz": 2
      }
    }
  },
  "by_topic_tree": [
    {
      "identifier": "5",
      "title": "Sicherheit",
      "total": 2,
      "own": 0,
      "by_type": {
        "Anderes": 2
      },
      "children": [
        {
          "identifier": "53",
          "title": "Kriegswirtschaft",
          "total": 2,
          "own": 2,
          "by_type": {
            "Anderes": 2
          }
        }
      ]
    },
    {
      "identifier": "8",
      "title": "Gesundheit, Soziale Sicherheit",
      "total": 2,
      "own": 0,
      "by_type": {
        "Anderes": 2
      },
      "children": [
        {
          "identifier": "81",
          "title": "Krankenanstalten, Rettungswesen, Umweltschutz",
          "total": 2,
          "own": 0,
          "by_type": {
            "Anderes": 2
          },
          "children": [
            {
              "identifier": "814",
              "title": "Umweltschutz",
              "total": 2,
              "own": 2,
              "by_type": {
                "Anderes": 2
              }
            }
          ]
        }
      ]
    }
  ],
  "by_global_category_tree": [
    {
      "identifier": "5",
      "title": "Verteidigung, Bevölkerungsschutz, Polizeiwesen",
      "total": 2,
      "own": 0,
      "by_type": {
        "Anderes": 2
      },
      "children": [
        {
          "identifier": "5.20",
          "title": "Bevölkerungsschutz",
          "total": 2,
          "own": 0,
          "by_type": {
            "Anderes": 2
          },
          "children": [
            {
              "identifier": "5.20.20",
              "title": "Landesversorgung",
              "total": 2,
              "own": 2,
              "by_type": {
                "Anderes": 2
              }
            }
          ]
        }
      ]
    },
    {
      "identifier": "7",
      "title": "Raumplanungs- und Baurecht, Enteignung, Öffentliche Werke, Energie, Verkehr, Umweltschutz, Naturschutz",
      "total": 2,
      "own": 0,
      "by_type": {
        "Anderes": 2
      },
      "children": [
        {
          "identifier": "7.60",
          "title": "Umweltschutz",
          "total": 2,
          "own": 0,
          "by_type": {
            "Anderes": 2
          },
          "children": [
            {
              "identifier": "7.60.20",
              "title": "Gewässerschutz",
              "total": 2,
              "own": 2,
              "by_type": {
                "Anderes": 2
              }
            }
          ]
        }
      ]
    }
  ],
  "by_language": {
    "de": 2,
    "fr": 2
  }
}