{
  "year": "2014",
  "entity": "AG",
  "total": 19,
  "categorized": 19,
  "uncategorized": 0,
  "by_type": {
    "Verordnung": {
      "total": 7,
      "by_topic": {
        "421 Volksschule": 2,
        "121 Bürgerrecht": 1,
        "210 Zivilgesetzbuch – Zivilstand – Obligationenrecht": 1,
        "615 Finanz- und Lastenausgleich": 1,
        "837 Krankenversicherung – Unfallversicherung": 1,
        "910 Allgemeines": 1
      },
      "by_global_category": {
        "4.10.30 Volksschule, Primarschule, Sekundarschule I": 2,
        "1.10.60 Bürgerrecht": 1,
        "9.20.10 Förderungsmassnahmen": 1
      }
    },
    "Interkantonale Vereinbarung": {
      "total": 7,
      "by_topic": {
        "530 Bund – Grenzwacht – Interkantonale Vereinbarungen": 2,
        "171 Allgemeines": 1,
        "311 Ausbildung – Berufsausübung": 1,
        "471 Allgemeines": 1,
        "533 Sportveranstaltungen": 1,
        "965 Dienstleistungsgewerbe": 1
      },
      "by_global_category": {
        "7.60.10 Abfälle": 1,
        "8.10.30.50 Chiropraktiker, Physiotherapeuten": 1,
        "4.100.10 Stipendien": 1,
        "5.40.10 Grenzwacht": 1,
        "5.30.10.30 Personal": 1,
        "4.180.30 Sport": 1,
        "9.50.10.10 Berufsausübungsbewilligungen": 1
      }
    },
    "Gesetz": {
      "total": 3,
      "by_topic": {
        "121 Bürgerrecht": 1,
        "615 Finanz- und Lastenausgleich": 1,
        "837 Krankenversicherung – Unfallversicherung": 1
      },
      "by_global_category": {
        "1.10.60 Bürgerrecht": 1
      }
    },
    "Verordnung des Parlaments (Dekret)": {
      "total": 2,
      "by_topic": {
        "615 Finanz- und Lastenausgleich": 1,
        "837 Krankenversicherung – Unfallversicherung": 1
      },
      "by_global_category": {
        "8.30.60.20 Prämienverbilligungen": 1
      }
    }
  },
  "by_topic_tree": [
    {
      "identifier": "1",
      "title": "Staatsrechtliche Grundlagen – Organisation",
      "total": 3,
      "own": 0,
      "by_type": {
        "Verordnung": 1,
        "Gesetz": 1,
        "Interkantonale Vereinbarung": 1
      },
      "children": [
        {
          "identifier": "12",
          "title": "Bürgerrecht – Aufenthalt – Niederlassung",
          "total": 2,
          "own": 0,
          "by_type": {
            "Verordnung": 1,
            "Gesetz": 1
          },
          "children": [
            {
              "identifier": "121",
              "title": "Bürgerrecht",
              "total": 2,
              "own": 2,
              "by_type": {
                "Verordnung": 1,
                "Gesetz": 1
              }
            }
          ]
        },
        {
          "identifier": "17",
          "title": "Gemeinden",
          "total": 1,
          "own": 0,
          "by_type": {
            "Interkantonale Vereinbarung": 1
          },
          "children": [
            {
              "identifier": "171",
              "title": "Allgemeines",
              "total": 1,
              "own": 1,
              "by_type": {
                "Interkantonale Vereinbarung": 1
              }
            }
          ]
        }
      ]
    },
    {
      "identifier": "2",
      "title": "Zivilrecht – Strafrecht – Rechtspflege",
      "total": 1,
      "own": 0,
      "by_type": {
        "Verordnung": 1
      },
      "children": [
        {
          "identifier": "21",
          "title": "Bundeszivilrecht: Ergänzende kantonale Erlasse",
          "total": 1,
          "own": 0,
          "by_type": {
            "Verordnung": 1
          },
          "children": [
            {
              "identifier": "210",
              "title": "Zivilgesetzbuch – Zivilstand – Obligationenrecht",
              "total": 1,
              "own": 1,
              "by_type": {
                "Verordnung": 1
              }
            }
          ]
        }
      ]
    },
    {
      "identifier": "3",
      "title": "Gesundheit",
      "total": 1,
      "own": 0,
      "by_type": {
        "Interkantonale Vereinbarung": 1
      },
      "children": [
        {
          "identifier": "31",
          "title": "Medizinalpersonen",
          "total": 1,
          "own": 0,
          "by_type": {
            "Interkantonale Vereinbarung": 1
          },
          "children": [
            {
              "identifier": "311",
              "title": "Ausbildung – Berufsausübung",
              "total": 1,
              "own": 1,
              "by_type": {
                "Interkantonale Vereinbarung": 1
              }
            }
          ]
        }
      ]
    },
    {
      "identifier": "4",
      "title": "Erziehung – Wissenschaft – Kultur",
      "total": 3,
      "own": 0,
      "by_type": {
        "Verordnung": 2,
        "Interkantonale Vereinbarung": 1
      },
      "children": [
        {
          "identifier": "42",
          "title": "Schulen",
          "total": 2,
          "own": 0,
          "by_type": {
            "Verordnung": 2
          },
          "children": [
            {
              "identifier": "421",
              "title": "Volksschule",
              "total": 2,
              "own": 2,
              "by_type": {
                "Verordnung": 2
              }
            }
          ]
        },
        {
          "identifier": "47",
          "title": "Ausbildungsbeiträge",
          "total": 1,
          "own": 0,
          "by_type": {
            "Interkantonale Vereinbarung": 1
          },
          "children": [
            {
              "identifier": "471",
              "title": "Allgemeines",
              "total": 1,
              "own": 1,
              "by_type": {
                "Interkantonale Vereinbarung": 1
              }
            }
          ]
        }
      ]
    },
    {
      "identifier": "5",
      "title": "Gesamtverteidigung – Polizei – Feuerwehr",
      "total": 3,
      "own": 0,
      "by_type": {
        "Interkantonale Vereinbarung": 3
      },
      "children": [
        {
          "identifier": "53",
          "title": "Polizei",
          "total": 3,
          "own": 0,
          "by_type": {
            "Interkantonale Vereinbarung": 3
          },
          "children": [
            {
              "identifier": "530",
              "title": "Bund – Grenzwacht – Interkantonale Vereinbarungen",
              "total": 2,
              "own": 2,
              "by_type": {
                "Interkantonale Vereinbarung": 2
              }
            },
            {
              "identifier": "533",
              "title": "Sportveranstaltungen",
              "total": 1,
              "own": 1,
              "by_type": {
                "Interkantonale Vereinbarung": 1
              }
            }
          ]
        }
      ]
    },
    {
      "identifier": "6",
      "title": "Finanzen – Steuern – Staatliche Monopole",
      "total": 3,
      "own": 0,
      "by_type": {
        "Gesetz": 1,
        "Verordnung des Parlaments (Dekret)": 1,
        "Verordnung": 1
      },
      "children": [
        {
          "identifier": "61",
          "title": "Finanzordnung",
          "total": 3,
          "own": 0,
          "by_type": {
            "Gesetz": 1,
            "Verordnung des Parlaments (Dekret)": 1,
            "Verordnung": 1
          },
          "children": [
            {
              "identifier": "615",
              "title": "Finanz- und Lastenausgleich",
              "total": 3,
              "own": 3,
              "by_type": {
                "Gesetz": 1,
                "Verordnung des Parlaments (Dekret)": 1,
                "Verordnung": 1
              }
            }
          ]
        }
      ]
    },
    {
      "identifier": "8",
      "title": "Soziale Sicherheit",
      "total": 3,
      "own": 0,
      "by_type": {
        "Gesetz": 1,
        "Verordnung": 1,
        "Verordnung des Parlaments (Dekret)": 1
      },
      "children": [
        {
          "identifier": "83",
          "title": "Sozialversicherungen",
          "total": 3,
          "own": 0,
          "by_type": {
            "Gesetz": 1,
            "Verordnung": 1,
            "Verordnung des Parlaments (Dekret)": 1
          },
          "children": [
            {
              "identifier": "837",
              "title": "Krankenversicherung – Unfallversicherung",
              "total": 3,
              "own": 3,
              "by_type": {
                "Gesetz": 1,
                "Verordnung": 1,
                "Verordnung des Parlaments (Dekret)": 1
              }
            }
          ]
        }
      ]
    },
    {
      "identifier": "9",
      "title": "Volkswirtschaft – Verkehr",
      "total": 2,
      "own": 0,
      "by_type": {
        "Verordnung": 1,
        "Interkantonale Vereinbarung": 1
      },
      "children": [
        {
          "identifier": "91",
          "title": "Landwirtschaft",
          "total": 1,
          "own": 0,
          "by_type": {
            "Verordnung": 1
          },
          "children": [
            {
              "identifier": "910",
              "title": "Allgemeines",
              "total": 1,
              "own": 1,
              "by_type": {
                "Verordnung": 1
              }
            }
          ]
        },
        {
          "identifier": "96",
          "title": "Industrie – Handel – Dienstleistungen",
          "total": 1,
          "own": 0,
          "by_type": {
            "Interkantonale Vereinbarung": 1
          },
          "children": [
            {
              "identifier": "965",
              "title": "Dienstleistungsgewerbe",
              "total": 1,
              "own": 1,
              "by_type": {
                "Interkantonale Vereinbarung": 1
              }
            }
          ]
        }
      ]
    }
  ],
  "by_global_category_tree": [
    {
      "identifier": "1",
      "title": "Staat",
      "total": 2,
      "own": 0,
      "by_type": {
        "Verordnung": 1,
        "Gesetz": 1
      },
      "children": [
        {
          "identifier": "1.10",
          "title": "Grundlagen",
          "total": 2,
          "own": 0,
          "by_type": {
            "Verordnung": 1,
            "Gesetz": 1
          },
          "children": [
            {
              "identifier": "1.10.60",
              "title": "Bürgerrecht",
              "total": 2,
              "own": 2,
              "by_type": {
                "Verordnung": 1,
                "Gesetz": 1
              }
            }
          ]
        }
      ]
    },
    {
      "identifier": "4",
      "title": "Schulwesen, Wissenschaft, Dokumentation und Kultur",
      "total": 4,
      "own": 0,
      "by_type": {
        "Verordnung": 2,
        "Interkantonale Vereinbarung": 2
      },
      "children": [
        {
          "identifier": "4.10",
          "title": "Vorschule, Primarstufe, Sekundarstufe I",
          "total": 2,
          "own": 0,
          "by_type": {
            "Verordnung": 2
          },
          "children": [
            {
              "identifier": "4.10.30",
              "title": "Volksschule, Primarschule, Sekundarschule I",
              "total": 2,
              "own": 2,
              "by_type": {
                "Verordnung": 2
              }
            }
          ]
        },
        {
          "identifier": "4.100",
          "title": "Ausbildungsbeiträge",
          "total": 1,
          "own": 0,
          "by_type": {
            "Interkantonale Vereinbarung": 1
          },
          "children": [
            {
              "identifier": "4.100.10",
              "title": "Stipendien",
              "total": 1,
              "own": 1,
              "by_type": {
                "Interkantonale Vereinbarung": 1
              }
            }
          ]
        },
        {
          "identifier": "4.180",
          "title": "Kunst, Kultur, Sport",
          "total": 1,
          "own": 0,
          "by_type": {
            "Interkantonale Vereinbarung": 1
          },
          "children": [
            {
              "identifier": "4.180.30",
              "title": "Sport",
              "total": 1,
              "own": 1,
              "by_type": {
                "Interkantonale Vereinbarung": 1
              }
            }
          ]
        }
      ]
    },
    {
      "identifier": "5",
      "title": "Verteidigung, Bevölkerungsschutz, Polizeiwesen",
      "total": 2,
      "own": 0,
      "by_type": {
        "Interkantonale Vereinbarung": 2
      },
      "children": [
        {
          "identifier": "5.30",
          "title": "Innere Sicherheit",
          "total": 1,
          "own": 0,
          "by_type": {
            "Interkantonale Vereinbarung": 1
          },
          "children": [
            {
              "identifier": "5.30.10",
              "title": "Polizei",
              "total": 1,
              "own": 0,
              "by_type": {
                "Interkantonale Vereinbarung": 1
              },
              "children": [
                {
                  "identifier": "5.30.10.30",
                  "title": "Personal",
                  "total": 1,
                  "own": 1,
                  "by_type": {
                    "Interkantonale Vereinbarung": 1
                  }
                }
              ]
            }
          ]
        },
        {
          "identifier": "5.40",
          "title": "Zölle",
          "total": 1,
          "own": 0,
          "by_type": {
            "Interkantonale Vereinbarung": 1
          },
          "children": [
            {
              "identifier": "5.40.10",
              "title": "Grenzwacht",
              "total": 1,
              "own": 1,
              "by_type": {
                "Interkantonale Vereinbarung": 1
              }
            }
          ]
        }
      ]
    },
    {
      "identifier": "7",
      "title": "Raumplanungs- und Baurecht, Enteignung, Öffentliche Werke, Energie, Verkehr, Umweltschutz, Naturschutz",
      "total": 1,
      "own": 0,
      "by_type": {
        "Interkantonale Vereinbarung": 1
      },
      "children": [
        {
          "identifier": "7.60",
          "title": "Umweltschutz",
          "total": 1,
          "own": 0,
          "by_type": {
            "Interkantonale Vereinbarung": 1
          },
          "children": [
            {
              "identifier": "7.60.10",
              "title": "Abfälle",
              "total": 1,
              "own": 1,
              "by_type": {
                "Interkantonale Vereinbarung": 1
              }
            }
          ]
        }
      ]
    },
    {
      "identifier": "8",
      "title": "Gesundheitswesen, Arbeit, Sozialversicherungen, Wohnen, Sozialhilfe",
      "total": 2,
      "own": 0,
      "by_type": {
        "Interkantonale Vereinbarung": 1,
        "Verordnung des Parlaments (Dekret)": 1
      },
      "children": [
        {
          "identifier": "8.10",
          "title": "Gesundheitswesen",
          "total": 1,
          "own": 0,
          "by_type": {
            "Interkantonale Vereinbarung": 1
          },
          "children": [
            {
              "identifier": "8.10.30",
              "title": "Medizinische Berufe",
              "total": 1,
              "own": 0,
              "by_type": {
                "Interkantonale Vereinbarung": 1
              },
              "children": [
                {
                  "identifier": "8.10.30.50",
                  "title": "Chiropraktiker, Physiotherapeuten",
                  "total": 1,
                  "own": 1,
                  "by_type": {
                    "Interkantonale Vereinbarung": 1
                  }
                }
              ]
            }
          ]
        },
        {
          "identifier": "8.30",
          "title": "Sozialversicherungsrecht",
          "total": 1,
          "own": 0,
          "by_type": {
            "Verordnung des Parlaments (Dekret)": 1
          },
          "children": [
            {
              "identifier": "8.30.60",
              "title": "KVG",
              "total": 1,
              "own": 0,
              "by_type": {
                "Verordnung des Parlaments (Dekret)": 1
              },
              "children": [
                {
                  "identifier": "8.30.60.20",
                  "title": "Prämienverbilligungen",
                  "total": 1,
                  "own": 1,
                  "by_type": {
                    "Verordnung des Parlaments (Dekret)": 1
                  }
                }
              ]
            }
          ]
        }
      ]
    },
    {
      "identifier": "9",
      "title": "Wirtschaft",
      "total": 2,
      "own": 0,
      "by_type": {
        "Verordnung": 1,
        "Interkantonale Vereinbarung": 1
      },
      "children": [
        {
          "identifier": "9.20",
          "title": "Landwirtschaft",
          "total": 1,
          "own": 0,
          "by_type": {
            "Verordnung": 1
          },
          "children": [
            {
              "identifier": "9.20.10",
              "title": "Förderungsmassnahmen",
              "total": 1,
              "own": 1,
              "by_type": {
                "Verordnung": 1
              }
            }
          ]
        },
        {
          "identifier": "9.50",
          "title": "Gewerbe",
          "total": 1,
          "own": 0,
          "by_type": {
            "Interkantonale Vereinbarung": 1
          },
          "children": [
            {
              "identifier": "9.50.10",
              "title": "Dienstleistungen",
              "total": 1,
              "own": 0,
              "by_type": {
                "Interkantonale Vereinbarung": 1
              },
              "children": [
                {
                  "identifier": "9.50.10.10",
                  "title": "Berufsausübungsbewilligungen",
                  "total": 1,
                  "own": 1,
                  "by_type": {
                    "Interkantonale Vereinbarung": 1
                  }
                }
              ]
            }
          ]
        }
      ]
    }
  ],
  "by_language": {
    "de": 19
  }
}