{
  "year": "1997",
  "entity": "GL",
  "total": 4,
  "categorized": 4,
  "uncategorized": 0,
  "by_type": {
    "Anderes": {
      "total": 2,
      "by_topic": {
        "VI C/4 Gebühren – Taxen – Abgaben": 1,
        "VII D/6 Öffentlicher Verkehr": 1
      },
      "by_global_category": {
        "6.20.70 Hundesteuern": 1,
        "6.10.30 Staatsbeiträge, Subventionen": 1
      }
    },
    "Verordnung des Parlaments (Dekret)": {
      "total": 1,
      "by_topic": {
        "IX D/5 Bildungs- und Forschungswesen": 1
      },
      "by_global_category": {}
    },
    "Gesetz": {
      "total": 1,
      "by_topic": {
        "VIII D/111 Kantonale Versicherung": 1
      },
      "by_global_category": {
        "8.30.30 AHV / IV": 1
      }
    }
  },
  "by_topic_tree": [
    {
      "identifier": "VI",
      "title": "Finanzen – Regalien",
      "total": 1,
      "own": 1,
      "by_type": {
        "Anderes": 1
      }
    },
    {
      "identifier": "VII",
      "title": "Raumplanung – Bauwesen – Öffentliche Werke – Verkehr – Energie",
      "total": 1,
      "own": 1,
      "by_type": {
        "Anderes": 1
      }
    },
    {
      "identifier": "VIII",
      "title": "Gesundheit – Umweltschutz – Arbeit – Soziale Sicherheit",
      "total": 1,
      "own": 1,
      "by_type": {
        "Gesetz": 1
      }
    },
    {
      "identifier": "IX",
      "title": "Volkswirtschaft",
      "total": 1,
      "own": 1,
      "by_type": {
        "Verordnung des Parlaments (Dekret)": 1
      }
    }
  ],
  "by_global_category_tree": [
    {
      "identifier": "6",
      "title": "Finanzen, Steuern, Monopole, Staatliche Unternehmen",
      "total": 2,
      "own": 0,
      "by_type": {
        "Anderes": 2
      },
      "children": [
        {
          "identifier": "6.10",
          "title": "Finanzen",
          "total": 1,
          "own": 0,
          "by_type": {
            "Anderes": 1
          },
          "children": [
            {
              "identifier": "6.10.30",
              "title": "Staatsbeiträge, Subventionen",
              "total": 1,
              "own": 1,
              "by_type": {
                "Anderes": 1
              }
            }
          ]
        },
        {
          "identifier": "6.20",
          "title": "Steuern",
          "total": 1,
          "own": 0,
          "by_type": {
            "Anderes": 1
          },
          "children": [
            {
              "identifier": "6.20.70",
              "title": "Hundesteuern",
              "total": 1,
              "own": 1,
              "by_type": {
                "Anderes": 1
              }
            }
          ]
        }
      ]
    },
    {
      "identifier": "8",
      "title": "Gesundheitswesen, Arbeit, Sozialversicherungen, Wohnen, Sozialhilfe",
      "total": 1,
      "own": 0,
      "by_type": {
        "Gesetz": 1
      },
      "children": [
        {
          "identifier": "8.30",
          "title": "Sozialversicherungsrecht",
          "total": 1,
          "own": 0,
          "by_type": {
            "Gesetz": 1
          },
          "children": [
            {
              "identifier": "8.30.30",
              "title": "AHV / IV",
              "total": 1,
              "own": 1,
              "by_type": {
                "Gesetz": 1
              }
            }
          ]
        }
      ]
    }
  ],
  "by_language": {
    "de": 4
  }
}