{
  "year": "2011",
  "entity": "VS",
  "total": 47,
  "categorized": 22,
  "uncategorized": 25,
  "by_type": {
    "Gesetz": {
      "total": 6,
      "by_topic": {
        "15 Grundrechte": 1,
        "170 Verantwortlichkeit, Information, Kompetenzen": 1,
        "177 Rechtsanwälte": 1,
        "21 Vollstreckung des Zivilrechts": 1,
        "50 Katastrophenschutz, Militärwesen": 1,
        "61 Finanzhaushalt": 1
      },
      "by_global_category": {
        "1.10.90.10 Gleichstellung von Mann und Frau": 1,
        "1.20.40 Staatshaftung": 1,
        "1.50.10.30 Unentgeltliche Rechtspflege": 1,
        "2.10.40.20 Erwerb von Grundstücke durch Personen im Ausland": 1,
        "5.10.30 Militärverwaltung": 1,
        "6.10.30 Staatsbeiträge, Subventionen": 1
      }
    },
    "Anderes": {
      "total": 6,
      "by_topic": {
        "45 Natur- und Heimatschutz": 2,
        "412 Berufsbildung": 1,
        "414 Höhere Ausbildung": 1,
        "417 Tertiärstufe und Weiterbildung": 1,
        "64 Steuern": 1
      },
      "by_global_category": {
        "7.70.10 Landschaftsschutz": 2,
        "4.90.20 Löhne, Entschädigungen": 1,
        "4.100.30 Schulgebühren": 1,
        "4.70.10 Erwachsenenbildung": 1,
        "1.20.70.10.60 Kantonale Rekurskommissionen": 1
      }
    },
    "Reglement": {
      "total": 5,
      "by_topic": {
        "173 Richterliche Behörden": 1,
        "178 Notare": 1,
        "413 Mittelschule": 1,
        "419 Pädagogische Hochschule": 1,
        "55 Kantonspolizei": 1
      },
      "by_global_category": {
        "1.10.120 Information der Öffentlichkeit": 1,
        "1.50.20.20 Gebühren, Tarife": 1,
        "4.20.10 Mittelschule": 1,
        "1.20.20.40.10 Anstellung": 1,
        "5.30.10.30 Personal": 1
      }
    },
    "Interkantonale Vereinbarung": {
      "total": 4,
      "by_topic": {
        "171 Grosser Rat": 1,
        "34 Strafvollzug": 1,
        "414 Höhere Ausbildung": 1,
        "55 Kantonspolizei": 1
      },
      "by_global_category": {
        "5.30.10.50 Polizeiliche Zusammenarbeit": 1
      }
    },
    "Verordnung": {
      "total": 1,
      "by_topic": {
        "748 Luftfahrt": 1
      },
      "by_global_category": {
        "7.50.70.10 Luftfahrzeuge": 1
      }
    }
  },
  "by_topic_tree": [
    {
      "identifier": "1",
      "title": "Staat, Volk, Behörden",
      "total": 6,
      "own": 0,
      "by_type": {
        "Gesetz": 3,
        "Reglement": 2,
        "Interkantonale Vereinbarung": 1
      },
      "children": [
        {
          "identifier": "15",
          "title": "Grundrechte",
          "total": 1,
          "own": 1,
          "by_type": {
            "Gesetz": 1
          }
        },
        {
          "identifier": "17",
          "title": "Behörden",
          "total": 5,
          "own": 0,
          "by_type": {
            "Gesetz": 2,
            "Reglement": 2,
            "Interkantonale Vereinbarung": 1
          },
          "children": [
            {
              "identifier": "170",
              "title": "Verantwortlichkeit, Information, Kompetenzen",
              "total": 1,
              "own": 1,
              "by_type": {
                "Gesetz": 1
              }
            },
            {
              "identifier": "171",
              "title": "Grosser Rat",
              "total": 1,
              "own": 1,
              "by_type": {
                "Interkantonale Vereinbarung": 1
              }
            },
            {
              "identifier": "173",
              "title": "Richterliche Behörden",
              "total": 1,
              "own": 1,
              "by_type": {
                "Reglement": 1
              }
            },
            {
              "identifier": "177",
              "title": "Rechtsanwälte",
              "total": 1,
              "own": 1,
              "by_type": {
                "Gesetz": 1
              }
            },
            {
              "identifier": "178",
              "title": "Notare",
              "total": 1,
              "own": 1,
              "by_type": {
                "Reglement": 1
              }
            }
          ]
        }
      ]
    },
    {
      "identifier": "2",
      "title": "Privatrecht, Zivilrechtspflege",
      "total": 1,
      "own": 0,
      "by_type": {
        "Gesetz": 1
      },
      "children": [
        {
          "identifier": "21",
          "title": "Vollstreckung des Zivilrechts",
          "total": 1,
          "own": 1,
          "by_type": {
            "Gesetz": 1
          }
        }
      ]
    },
    {
      "identifier": "3",
      "title": "Strafrechtspflege - Strafvollzug",
      "total": 1,
      "own": 0,
      "by_type": {
        "Interkantonale Vereinbarung": 1
      },
      "children": [
        {
          "identifier": "34",
          "title": "Strafvollzug",
          "total": 1,
          "own": 1,
          "by_type": {
            "Interkantonale Vereinbarung": 1
          }
        }
      ]
    },
    {
      "identifier": "4",
      "title": "Schule - Wissenschaft - Kultur",
      "total": 8,
      "own": 0,
      "by_type": {
        "Anderes": 5,
        "Reglement": 2,
        "Interkantonale Vereinbarung": 1
      },
      "children": [
        {
          "identifier": "41",
          "title": "Schulen",
          "total": 6,
          "own": 0,
          "by_type": {
            "Anderes": 3,
            "Reglement": 2,
            "Interkantonale Vereinbarung": 1
          },
          "children": [
            {
              "identifier": "412",
              "title": "Berufsbildung",
              "total": 1,
              "own": 1,
              "by_type": {
                "Anderes": 1
              }
            },
            {
              "identifier": "413",
              "title": "Mittelschule",
              "total": 1,
              "own": 1,
              "by_type": {
                "Reglement": 1
              }
            },
            {
              "identifier": "414",
              "title": "Höhere Ausbildung",
              "total": 2,
              "own": 2,
              "by_type": {
                "Interkantonale Vereinbarung": 1,
                "Anderes": 1
              }
            },
            {
              "identifier": "417",
              "title": "Tertiärstufe und Weiterbildung",
              "total": 1,
              "own": 1,
              "by_type": {
                "Anderes": 1
              }
            },
            {
              "identifier": "419",
              "title": "Pädagogische Hochschule",
              "total": 1,
              "own": 1,
              "by_type": {
                "Reglement": 1
              }
            }
          ]
        },
        {
          "identifier": "45",
          "title": "Natur- und Heimatschutz",
          "total": 2,
          "own": 2,
          "by_type": {
            "Anderes": 2
          }
        }
      ]
    },
    {
      "identifier": "5",
      "title": "Sicherheit",
      "total": 3,
      "own": 0,
      "by_type": {
        "Gesetz": 1,
        "Reglement": 1,
        "Interkantonale Vereinbarung": 1
      },
      "children": [
        {
          "identifier": "50",
          "title": "Katastrophenschutz, Militärwesen",
          "total": 1,
          "own": 1,
          "by_type": {
            "Gesetz": 1
          }
        },
        {
          "identifier": "55",
          "title": "Kantonspolizei",
          "total": 2,
          "own": 2,
          "by_type": {
            "Reglement": 1,
            "Interkantonale Vereinbarung": 1
          }
        }
      ]
    },
    {
      "identifier": "6",
      "title": "Finanzen und Steuern",
      "total": 2,
      "own": 0,
      "by_type": {
        "Gesetz": 1,
        "Anderes": 1
      },
      "children": [
        {
          "identifier": "61",
          "title": "Finanzhaushalt",
          "total": 1,
          "own": 1,
          "by_type": {
            "Gesetz": 1
          }
        },
        {
          "identifier": "64",
          "title": "Steuern",
          "total": 1,
          "own": 1,
          "by_type": {
            "Anderes": 1
          }
        }
      ]
    },
    {
      "identifier": "7",
      "title": "Öffentliche Werke, Energie, Verkehr",
      "total": 1,
      "own": 0,
      "by_type": {
        "Verordnung": 1
      },
      "children": [
        {
          "identifier": "74",
          "title": "Verkehr",
          "total": 1,
          "own": 0,
          "by_type": {
            "Verordnung": 1
          },
          "children": [
            {
              "identifier": "748",
              "title": "Luftfahrt",
              "total": 1,
              "own": 1,
              "by_type": {
                "Verordnung": 1
              }
            }
          ]
        }
      ]
    }
  ],
  "by_global_category_tree": [
    {
      "identifier": "1",
      "title": "Staat",
      "total": 7,
      "own": 0,
      "by_type": {
        "Gesetz": 3,
        "Reglement": 3,
        "Anderes": 1
      },
      "children": [
        {
          "identifier": "1.10",
          "title": "Grundlagen",
          "total": 2,
          "own": 0,
          "by_type": {
            "Gesetz": 1,
            "Reglement": 1
          },
          "children": [
            {
              "identifier": "1.10.90",
              "title": "Grundrechte, Politische Rechte",
              "total": 1,
              "own": 0,
              "by_type": {
                "Gesetz": 1
              },
              "children": [
                {
                  "identifier": "1.10.90.10",
                  "title": "Gleichstellung von Mann und Frau",
                  "total": 1,
                  "own": 1,
                  "by_type": {
                    "Gesetz": 1
                  }
                }
              ]
            },
            {
              "identifier": "1.10.120",
              "title": "Information der Öffentlichkeit",
              "total": 1,
              "own": 1,
              "by_type": {
                "Reglement": 1
              }
            }
          ]
        },
        {
          "identifier": "1.20",
          "title": "Behörden",
          "total": 3,
          "own": 0,
          "by_type": {
            "Reglement": 1,
            "Gesetz": 1,
            "Anderes": 1
          },
          "children": [
            {
              "identifier": "1.20.20",
              "title": "Regierung und Verwaltung",
              "total": 1,
              "own": 0,
              "by_type": {
                "Reglement": 1
              },
              "children": [
                {
                  "identifier": "1.20.20.40",
                  "title": "Personalrecht",
                  "total": 1,
                  "own": 0,
                  "by_type": {
                    "Reglement": 1
                  },
                  "children": [
                    {
                      "identifier": "1.20.20.40.10",
                      "title": "Anstellung",
                      "total": 1,
                      "own": 1,
                      "by_type": {
                        "Reglement": 1
                      }
                    }
                  ]
                }
              ]
            },
            {
              "identifier": "1.20.40",
              "title": "Staatshaftung",
              "total": 1,
              "own": 1,
              "by_type": {
                "Gesetz": 1
              }
            },
            {
              "identifier": "1.20.70",
              "title": "Gerichtsorganisation",
              "total": 1,
              "own": 0,
              "by_type": {
                "Anderes": 1
              },
              "children": [
                {
                  "identifier": "1.20.70.10",
                  "title": "Gerichtsbehörden",
                  "total": 1,
                  "own": 0,
                  "by_type": {
                    "Anderes": 1
                  },
                  "children": [
                    {
                      "identifier": "1.20.70.10.60",
                      "title": "Kantonale Rekurskommissionen",
                      "total": 1,
                      "own": 1,
                      "by_type": {
                        "Anderes": 1
                      }
                    }
                  ]
                }
              ]
            }
          ]
        },
        {
          "identifier": "1.50",
          "title": "Juristische Berufe",
          "total": 2,
          "own": 0,
          "by_type": {
            "Gesetz": 1,
            "Reglement": 1
          },
          "children": [
            {
              "identifier": "1.50.10",
              "title": "Anwälte",
              "total": 1,
              "own": 0,
              "by_type": {
                "Gesetz": 1
              },
              "children": [
                {
                  "identifier": "1.50.10.30",
                  "title": "Unentgeltliche Rechtspflege",
                  "total": 1,
                  "own": 1,
                  "by_type": {
                    "Gesetz": 1
                  }
                }
              ]
            },
            {
              "identifier": "1.50.20",
              "title": "Notare",
              "total": 1,
              "own": 0,
              "by_type": {
                "Reglement": 1
              },
              "children": [
                {
                  "identifier": "1.50.20.20",
                  "title": "Gebühren, Tarife",
                  "total": 1,
                  "own": 1,
                  "by_type": {
                    "Reglement": 1
                  }
                }
              ]
            }
          ]
        }
      ]
    },
    {
      "identifier": "2",
      "title": "Zivilrecht",
      "total": 1,
      "own": 0,
      "by_type": {
        "Gesetz": 1
      },
      "children": [
        {
          "identifier": "2.10",
          "title": "Einführungsgesetzgebung zum ZGB",
          "total": 1,
          "own": 0,
          "by_type": {
            "Gesetz": 1
          },
          "children": [
            {
              "identifier": "2.10.40",
              "title": "Sachenrecht",
              "total": 1,
              "own": 0,
              "by_type": {
                "Gesetz": 1
              },
              "children": [
                {
                  "identifier": "2.10.40.20",
                  "title": "Erwerb von Grundstücke durch Personen im Ausland",
                  "total": 1,
                  "own": 1,
                  "by_type": {
                    "Gesetz": 1
                  }
                }
              ]
            }
          ]
        }
      ]
    },
    {
      "identifier": "4",
      "title": "Schulwesen, Wissenschaft, Dokumentation und Kultur",
      "total": 4,
      "own": 0,
      "by_type": {
        "Anderes": 3,
        "Reglement": 1
      },
      "children": [
        {
          "identifier": "4.20",
          "title": "Sekundarstufe II",
          "total": 1,
          "own": 0,
          "by_type": {
            "Reglement": 1
          },
          "children": [
            {
              "identifier": "4.20.10",
              "title": "Mittelschule",
              "total": 1,
              "own": 1,
              "by_type": {
                "Reglement": 1
              }
            }
          ]
        },
        {
          "identifier": "4.70",
          "title": "Weiterbildung (Quartärstufe)",
          "total": 1,
          "own": 0,
          "by_type": {
            "Anderes": 1
          },
          "children": [
            {
              "identifier": "4.70.10",
              "title": "Erwachsenenbildung",
              "total": 1,
              "own": 1,
              "by_type": {
                "Anderes": 1
              }
            }
          ]
        },
        {
          "identifier": "4.90",
          "title": "Lehrkörper",
          "total": 1,
          "own": 0,
          "by_type": {
            "Anderes": 1
          },
          "children": [
            {
              "identifier": "4.90.20",
              "title": "Löhne, Entschädigungen",
              "total": 1,
              "own": 1,
              "by_type": {
                "Anderes": 1
              }
            }
          ]
        },
        {
          "identifier": "4.100",
          "title": "Ausbildungsbeiträge",
          "total": 1,
          "own": 0,
          "by_type": {
            "Anderes": 1
          },
          "children": [
            {
              "identifier": "4.100.30",
              "title": "Schulgebühren",
              "total": 1,
              "own": 1,
              "by_type": {
                "Anderes": 1
              }
            }
          ]
        }
      ]
    },
    {
      "identifier": "5",
      "title": "Verteidigung, Bevölkerungsschutz, Polizeiwesen",
      "total": 3,
      "own": 0,
      "by_type": {
        "Gesetz": 1,
        "Reglement": 1,
        "Interkantonale Vereinbarung": 1
      },
      "children": [
        {
          "identifier": "5.10",
          "title": "Verteidigung",
          "total": 1,
          "own": 0,
          "by_type": {
            "Gesetz": 1
          },
          "children": [
            {
              "identifier": "5.10.30",
              "title": "Militärverwaltung",
              "total": 1,
              "own": 1,
              "by_type": {
                "Gesetz": 1
              }
            }
          ]
        },
        {
          "identifier": "5.30",
          "title": "Innere Sicherheit",
          "total": 2,
          "own": 0,
          "by_type": {
            "Reglement": 1,
            "Interkantonale Vereinbarung": 1
          },
          "children": [
            {
              "identifier": "5.30.10",
              "title": "Polizei",
              "total": 2,
              "own": 0,
              "by_type": {
                "Reglement": 1,
                "Interkantonale Vereinbarung": 1
              },
              "children": [
                {
                  "identifier": "5.30.10.30",
                  "title": "Personal",
                  "total": 1,
                  "own": 1,
                  "by_type": {
                    "Reglement": 1
                  }
                },
                {
                  "identifier": "5.30.10.50",
                  "title": "Polizeiliche Zusammenarbeit",
                  "total": 1,
                  "own": 1,
                  "by_type": {
                    "Interkantonale Vereinbarung": 1
                  }
                }
              ]
            }
          ]
        }
      ]
    },
    {
      "identifier": "6",
      "title": "Finanzen, Steuern, Monopole, Staatliche Unternehmen",
      "total": 1,
      "own": 0,
      "by_type": {
        "Gesetz": 1
      },
      "children": [
        {
          "identifier": "6.10",
          "title": "Finanzen",
          "total": 1,
          "own": 0,
          "by_type": {
            "Gesetz": 1
          },
          "children": [
            {
              "identifier": "6.10.30",
              "title": "Staatsbeiträge, Subventionen",
              "total": 1,
              "own": 1,
              "by_type": {
                "Gesetz": 1
              }
            }
          ]
        }
      ]
    },
    {
      "identifier": "7",
      "title": "Raumplanungs- und Baurecht, Enteignung, Öffentliche Werke, Energie, Verkehr, Umweltschutz, Naturschutz",
      "total": 3,
      "own": 0,
      "by_type": {
        "Anderes": 2,
        "Verordnung": 1
      },
      "children": [
        {
          "identifier": "7.50",
          "title": "Verkehr",
          "total": 1,
          "own": 0,
          "by_type": {
            "Verordnung": 1
          },
          "children": [
            {
              "identifier": "7.50.70",
              "title": "Luftfahrt",
              "total": 1,
              "own": 0,
              "by_type": {
                "Verordnung": 1
              },
              "children": [
                {
                  "identifier": "7.50.70.10",
                  "title": "Luftfahrzeuge",
                  "total": 1,
                  "own": 1,
                  "by_type": {
                    "Verordnung": 1
                  }
                }
              ]
            }
          ]
        },
        {
          "identifier": "7.70",
          "title": "Natur- und Heimatschutz",
          "total": 2,
          "own": 0,
          "by_type": {
            "Anderes": 2
          },
          "children": [
            {
              "identifier": "7.70.10",
              "title": "Landschaftsschutz",
              "total": 2,
              "own": 2,
              "by_type": {
                "Anderes": 2
              }
            }
          ]
        }
      ]
    }
  ],
  "by_language": {
    "de": 25,
    "fr": 22
  }
}