{
  "year": "2017",
  "entity": "OW",
  "total": 31,
  "categorized": 31,
  "uncategorized": 0,
  "by_type": {
    "Anderes": {
      "total": 19,
      "by_topic": {
        "930 Forstwirtschaft": 7,
        "540 Bevölkerungsschutz": 2,
        "113 Niederlassung, Aufenthalt, Ausländerrecht": 1,
        "211 Personen- und Familienrecht": 1,
        "330 Strafvollzug, Strafregister": 1,
        "410 Schulen": 1,
        "651 Jagd, Fischerei": 1,
        "710 Raum- und Bauordnung": 1,
        "720 Strassen und Wege": 1,
        "786 Natur- und Landschaftsschutz": 1,
        "814 Heilmittel, Betäubungsmittel, Gifte": 1,
        "921 Förderung der Landwirtschaft": 1
      },
      "by_global_category": {
        "1.10.70.20.10 Asylwesen": 1,
        "2.10.20.20 Pflegekinder, Adoption": 1,
        "4.80.20 Hochbegabtenförderung": 1,
        "7.10.10 Pläne": 1,
        "7.30.30.20 Fuss- und Wanderwege": 1,
        "7.70.10 Landschaftsschutz": 1,
        "7.60.70 Gifte, Chemikalien": 1,
        "6.10.30 Staatsbeiträge, Subventionen": 1,
        "9.30.20 Forstpersonal": 1
      }
    },
    "Gesetz": {
      "total": 7,
      "by_topic": {
        "210 Zivilrecht": 2,
        "870 Sozialhilfe, Entwicklungshilfe": 2,
        "643 Gebühren": 1,
        "921 Förderung der Landwirtschaft": 1,
        "971 Gastgewerbe und Tourismus": 1
      },
      "by_global_category": {
        "1.50.20.30 Öffentliche Beurkundung": 1,
        "1.20.20.60 Verwaltungsgebühren": 1,
        "8.70.10 Sozialhilfe": 1,
        "4.10.10 Krippen, Kinderhorte": 1,
        "2.20.10.20.10 Landwirtschaftliche Pacht": 1,
        "9.50.10.20 Tourismus": 1
      }
    },
    "Verordnung des Parlaments (Dekret)": {
      "total": 5,
      "by_topic": {
        "213 Sachenrecht, Grundbuch, Grundstückschätzungen": 2,
        "419 Ausbildungsbeiträge": 1,
        "710 Raum- und Bauordnung": 1,
        "971 Gastgewerbe und Tourismus": 1
      },
      "by_global_category": {
        "2.10.40.30 Grundbuch und Grundbuchvermessung": 2,
        "9.50.10.20 Tourismus": 1
      }
    }
  },
  "by_topic_tree": [
    {
      "identifier": "1",
      "title": "GRUNDLAGEN UND ORGANISATION",
      "total": 1,
      "own": 0,
      "by_type": {
        "Anderes": 1
      },
      "children": [
        {
          "identifier": "113",
          "title": "Niederlassung, Aufenthalt, Ausländerrecht",
          "total": 1,
          "own": 1,
          "by_type": {
            "Anderes": 1
          }
        }
      ]
    },
    {
      "identifier": "2",
      "title": "ZIVILRECHT, VOLLSTRECKUNG",
      "total": 5,
      "own": 0,
      "by_type": {
        "Gesetz": 2,
        "Verordnung des Parlaments (Dekret)": 2,
        "Anderes": 1
      },
      "children": [
        {
          "identifier": "210",
          "title": "Zivilrecht",
          "total": 2,
          "own": 2,
          "by_type": {
            "Gesetz": 2
          }
        },
        {
          "identifier": "211",
          "title": "Personen- und Familienrecht",
          "total": 1,
          "own": 1,
          "by_type": {
            "Anderes": 1
          }
        },
        {
          "identifier": "213",
          "title": "Sachenrecht, Grundbuch, Grundstückschätzungen",
          "total": 2,
          "own": 2,
          "by_type": {
            "Verordnung des Parlaments (Dekret)": 2
          }
        }
      ]
    },
    {
      "identifier": "3",
      "title": "STRAFRECHT",
      "total": 1,
      "own": 0,
      "by_type": {
        "Anderes": 1
      },
      "children": [
        {
          "identifier": "330",
          "title": "Strafvollzug, Strafregister",
          "total": 1,
          "own": 1,
          "by_type": {
            "Anderes": 1
          }
        }
      ]
    },
    {
      "identifier": "4",
      "title": "ERZIEHUNG, BILDUNG, KULTUR",
      "total": 2,
      "own": 0,
      "by_type": {
        "Anderes": 1,
        "Verordnung des Parlaments (Dekret)": 1
      },
      "children": [
        {
          "identifier": "410",
          "title": "Schulen",
          "total": 1,
          "own": 1,
          "by_type": {
            "Anderes": 1
          }
        },
        {
          "identifier": "419",
          "title": "Ausbildungsbeiträge",
          "total": 1,
          "own": 1,
          "by_type": {
            "Verordnung des Parlaments (Dekret)": 1
          }
        }
      ]
    },
    {
      "identifier": "5",
      "title": "SICHERHEIT, BEVÖLKERUNGSSCHUTZ",
      "total": 2,
      "own": 0,
      "by_type": {
        "Anderes": 2
      },
      "children": [
        {
          "identifier": "540",
          "title": "Bevölkerungsschutz",
          "total": 2,
          "own": 2,
          "by_type": {
            "Anderes": 2
          }
        }
      ]
    },
    {
      "identifier": "6",
      "title": "FINANZEN, REGALIEN, STAATLICHE UNTERNEHMUNGEN",
      "total": 2,
      "own": 0,
      "by_type": {
        "Gesetz": 1,
        "Anderes": 1
      },
      "children": [
        {
          "identifier": "643",
          "title": "Gebühren",
          "total": 1,
          "own": 1,
          "by_type": {
            "Gesetz": 1
          }
        },
        {
          "identifier": "651",
          "title": "Jagd, Fischerei",
          "total": 1,
          "own": 1,
          "by_type": {
            "Anderes": 1
          }
        }
      ]
    },
    {
      "identifier": "7",
      "title": "RAUM- UND BAUORDNUNG, ÖFFENTLICHE WERKE, ENERGIE, VERKEHR, UMWELTSCHUTZ",
      "total": 4,
      "own": 0,
      "by_type": {
        "Anderes": 3,
        "Verordnung des Parlaments (Dekret)": 1
      },
      "children": [
        {
          "identifier": "710",
          "title": "Raum- und Bauordnung",
          "total": 2,
          "own": 2,
          "by_type": {
            "Verordnung des Parlaments (Dekret)": 1,
            "Anderes": 1
          }
        },
        {
          "identifier": "720",
          "title": "Strassen und Wege",
          "total": 1,
          "own": 1,
          "by_type": {
            "Anderes": 1
          }
        },
        {
          "identifier": "786",
          "title": "Natur- und Landschaftsschutz",
          "total": 1,
          "own": 1,
          "by_type": {
            "Anderes": 1
          }
        }
      ]
    },
    {
      "identifier": "8",
      "title": "GESUNDHEIT, ARBEIT, SOZIALE SICHERHEIT",
      "total": 3,
      "own": 0,
      "by_type": {
        "Gesetz": 2,
        "Anderes": 1
      },
      "children": [
        {
          "identifier": "814",
          "title": "Heilmittel, Betäubungsmittel, Gifte",
          "total": 1,
          "own": 1,
          "by_type": {
            "Anderes": 1
          }
        },
        {
          "identifier": "870",
          "title": "Sozialhilfe, Entwicklungshilfe",
          "total": 2,
          "own": 2,
          "by_type": {
            "Gesetz": 2
          }
        }
      ]
    },
    {
      "identifier": "9",
      "title": "VOLKSWIRTSCHAFT",
      "total": 11,
      "own": 0,
      "by_type": {
        "Anderes": 8,
        "Gesetz": 2,
        "Verordnung des Parlaments (Dekret)": 1
      },
      "children": [
        {
          "identifier": "921",
          "title": "Förderung der Landwirtschaft",
          "total": 2,
          "own": 2,
          "by_type": {
            "Gesetz": 1,
            "Anderes": 1
          }
        },
        {
          "identifier": "930",
          "title": "Forstwirtschaft",
          "total": 7,
          "own": 7,
          "by_type": {
            "Anderes": 7
          }
        },
        {
          "identifier": "971",
          "title": "Gastgewerbe und Tourismus",
          "total": 2,
          "own": 2,
          "by_type": {
            "Gesetz": 1,
            "Verordnung des Parlaments (Dekret)": 1
          }
        }
      ]
    }
  ],
  "by_global_category_tree": [
    {
      "identifier": "1",
      "title": "Staat",
      "total": 3,
      "own": 0,
      "by_type": {
        "Gesetz": 2,
        "Anderes": 1
      },
      "children": [
        {
          "identifier": "1.10",
          "title": "Grundlagen",
          "total": 1,
          "own": 0,
          "by_type": {
            "Anderes": 1
          },
          "children": [
            {
              "identifier": "1.10.70",
              "title": "Niederlassung und Aufenthalt",
              "total": 1,
              "own": 0,
              "by_type": {
                "Anderes": 1
              },
              "children": [
                {
                  "identifier": "1.10.70.20",
                  "title": "Niederlassung und Aufenthalt Ausländer",
                  "total": 1,
                  "own": 0,
                  "by_type": {
                    "Anderes": 1
                  },
                  "children": [
                    {
                      "identifier": "1.10.70.20.10",
                      "title": "Asylwesen",
                      "total": 1,
                      "own": 1,
                      "by_type": {
                        "Anderes": 1
                      }
                    }
                  ]
                }
              ]
            }
          ]
        },
        {
          "identifier": "1.20",
          "title": "Behörden",
          "total": 1,
          "own": 0,
          "by_type": {
            "Gesetz": 1
          },
          "children": [
            {
              "identifier": "1.20.20",
              "title": "Regierung und Verwaltung",
              "total": 1,
              "own": 0,
              "by_type": {
                "Gesetz": 1
              },
              "children": [
                {
                  "identifier": "1.20.20.60",
                  "title": "Verwaltungsgebühren",
                  "total": 1,
                  "own": 1,
                  "by_type": {
                    "Gesetz": 1
                  }
                }
              ]
            }
          ]
        },
        {
          "identifier": "1.50",
          "title": "Juristische Berufe",
          "total": 1,
          "own": 0,
          "by_type": {
            "Gesetz": 1
          },
          "children": [
            {
              "identifier": "1.50.20",
              "title": "Notare",
              "total": 1,
              "own": 0,
              "by_type": {
                "Gesetz": 1
              },
              "children": [
                {
                  "identifier": "1.50.20.30",
                  "title": "Öffentliche Beurkundung",
                  "total": 1,
                  "own": 1,
                  "by_type": {
                    "Gesetz": 1
                  }
                }
              ]
            }
          ]
        }
      ]
    },
    {
      "identifier": "2",
      "title": "Zivilrecht",
      "total": 4,
      "own": 0,
      "by_type": {
        "Verordnung des Parlaments (Dekret)": 2,
        "Anderes": 1,
        "Gesetz": 1
      },
      "children": [
        {
          "identifier": "2.10",
          "title": "Einführungsgesetzgebung zum ZGB",
          "total": 3,
          "own": 0,
          "by_type": {
            "Verordnung des Parlaments (Dekret)": 2,
            "Anderes": 1
          },
          "children": [
            {
              "identifier": "2.10.20",
              "title": "Familienrecht",
              "total": 1,
              "own": 0,
              "by_type": {
                "Anderes": 1
              },
              "children": [
                {
                  "identifier": "2.10.20.20",
                  "title": "Pflegekinder, Adoption",
                  "total": 1,
                  "own": 1,
                  "by_type": {
                    "Anderes": 1
                  }
                }
              ]
            },
            {
              "identifier": "2.10.40",
              "title": "Sachenrecht",
              "total": 2,
              "own": 0,
              "by_type": {
                "Verordnung des Parlaments (Dekret)": 2
              },
              "children": [
                {
                  "identifier": "2.10.40.30",
                  "title": "Grundbuch und Grundbuchvermessung",
                  "total": 2,
                  "own": 2,
                  "by_type": {
                    "Verordnung des Parlaments (Dekret)": 2
                  }
                }
              ]
            }
          ]
        },
        {
          "identifier": "2.20",
          "title": "Einführungsgesetzgebung OR",
          "total": 1,
          "own": 0,
          "by_type": {
            "Gesetz": 1
          },
          "children": [
            {
              "identifier": "2.20.10",
              "title": "Vertragsverhältnisse",
              "total": 1,
              "own": 0,
              "by_type": {
                "Gesetz": 1
              },
              "children": [
                {
                  "identifier": "2.20.10.20",
                  "title": "Miete und Pacht",
                  "total": 1,
                  "own": 0,
                  "by_type": {
                    "Gesetz": 1
                  },
                  "children": [
                    {
                      "identifier": "2.20.10.20.10",
                      "title": "Landwirtschaftliche Pacht",
                      "total": 1,
                      "own": 1,
                      "by_type": {
                        "Gesetz": 1
                      }
                    }
                  ]
                }
              ]
            }
          ]
        }
      ]
    },
    {
      "identifier": "4",
      "title": "Schulwesen, Wissenschaft, Dokumentation und Kultur",
      "total": 2,
      "own": 0,
      "by_type": {
        "Gesetz": 1,
        "Anderes": 1
      },
      "children": [
        {
          "identifier": "4.10",
          "title": "Vorschule, Primarstufe, Sekundarstufe I",
          "total": 1,
          "own": 0,
          "by_type": {
            "Gesetz": 1
          },
          "children": [
            {
              "identifier": "4.10.10",
              "title": "Krippen, Kinderhorte",
              "total": 1,
              "own": 1,
              "by_type": {
                "Gesetz": 1
              }
            }
          ]
        },
        {
          "identifier": "4.80",
          "title": "Sonderpädagogik",
          "total": 1,
          "own": 0,
          "by_type": {
            "Anderes": 1
          },
          "children": [
            {
              "identifier": "4.80.20",
              "title": "Hochbegabtenförderung",
              "total": 1,
              "own": 1,
              "by_type": {
                "Anderes": 1
              }
            }
          ]
        }
      ]
    },
    {
      "identifier": "6",
      "title": "Finanzen, Steuern, Monopole, Staatliche Unternehmen",
      "total": 1,
      "own": 0,
      "by_type": {
        "Anderes": 1
      },
      "children": [
        {
          "identifier": "6.10",
          "title": "Finanzen",
          "total": 1,
          "own": 0,
          "by_type": {
            "Anderes": 1
          },
          "children": [
            {
              "identifier": "6.10.30",
              "title": "Staatsbeiträge, Subventionen",
              "total": 1,
              "own": 1,
              "by_type": {
                "Anderes": 1
              }
            }
          ]
        }
      ]
    },
    {
      "identifier": "7",
      "title": "Raumplanungs- und Baurecht, Enteignung, Öffentliche Werke, Energie, Verkehr, Umweltschutz, Naturschutz",
      "total": 4,
      "own": 0,
      "by_type": {
        "Anderes": 4
      },
      "children": [
        {
          "identifier": "7.10",
          "title": "Raumplanungs- und Baurecht",
          "total": 1,
          "own": 0,
          "by_type": {
            "Anderes": 1
          },
          "children": [
            {
              "identifier": "7.10.10",
              "title": "Pläne",
              "total": 1,
              "own": 1,
              "by_type": {
                "Anderes": 1
              }
            }
          ]
        },
        {
          "identifier": "7.30",
          "title": "Öffentliche Werke",
          "total": 1,
          "own": 0,
          "by_type": {
            "Anderes": 1
          },
          "children": [
            {
              "identifier": "7.30.30",
              "title": "Strassen",
              "total": 1,
              "own": 0,
              "by_type": {
                "Anderes": 1
              },
              "children": [
                {
                  "identifier": "7.30.30.20",
                  "title": "Fuss- und Wanderwege",
                  "total": 1,
                  "own": 1,
                  "by_type": {
                    "Anderes": 1
                  }
                }
              ]
            }
          ]
        },
        {
          "identifier": "7.60",
          "title": "Umweltschutz",
          "total": 1,
          "own": 0,
          "by_type": {
            "Anderes": 1
          },
          "children": [
            {
              "identifier": "7.60.70",
              "title": "Gifte, Chemikalien",
              "total": 1,
              "own": 1,
              "by_type": {
                "Anderes": 1
              }
            }
          ]
        },
        {
          "identifier": "7.70",
          "title": "Natur- und Heimatschutz",
          "total": 1,
          "own": 0,
          "by_type": {
            "Anderes": 1
          },
          "children": [
            {
              "identifier": "7.70.10",
              "title": "Landschaftsschutz",
              "total": 1,
              "own": 1,
              "by_type": {
                "Anderes": 1
              }
            }
          ]
        }
      ]
    },
    {
      "identifier": "8",
      "title": "Gesundheitswesen, Arbeit, Sozialversicherungen, Wohnen, Sozialhilfe",
      "total": 1,
      "own": 0,
      "by_type": {
        "Gesetz": 1
      },
      "children": [
        {
          "identifier": "8.70",
          "title": "Fürsorge",
          "total": 1,
          "own": 0,
          "by_type": {
            "Gesetz": 1
          },
          "children": [
            {
              "identifier": "8.70.10",
              "title": "Sozialhilfe",
              "total": 1,
              "own": 1,
              "by_type": {
                "Gesetz": 1
              }
            }
          ]
        }
      ]
    },
    {
      "identifier": "9",
      "title": "Wirtschaft",
      "total": 3,
      "own": 0,
      "by_type": {
        "Anderes": 1,
        "Gesetz": 1,
        "Verordnung des Parlaments (Dekret)": 1
      },
      "children": [
        {
          "identifier": "9.30",
          "title": "Forstwirtschaft",
          "total": 1,
          "own": 0,
          "by_type": {
            "Anderes": 1
          },
          "children": [
            {
              "identifier": "9.30.20",
              "title": "Forstpersonal",
              "total": 1,
              "own": 1,
              "by_type": {
                "Anderes": 1
              }
            }
          ]
        },
        {
          "identifier": "9.50",
          "title": "Gewerbe",
          "total": 2,
          "own": 0,
          "by_type": {
            "Gesetz": 1,
            "Verordnung des Parlaments (Dekret)": 1
          },
          "children": [
            {
              "identifier": "9.50.10",
              "title": "Dienstleistungen",
              "total": 2,
              "own": 0,
              "by_type": {
                "Gesetz": 1,
                "Verordnung des Parlaments (Dekret)": 1
              },
              "children": [
                {
                  "identifier": "9.50.10.20",
                  "title": "Tourismus",
                  "total": 2,
                  "own": 2,
                  "by_type": {
                    "Gesetz": 1,
                    "Verordnung des Parlaments (Dekret)": 1
                  }
                }
              ]
            }
          ]
        }
      ]
    }
  ],
  "by_language": {
    "de": 31
  }
}