{
  "year": "1978",
  "entity": "VS",
  "total": 2,
  "categorized": 2,
  "uncategorized": 0,
  "by_type": {
    "Anderes": {
      "total": 2,
      "by_topic": {
        "817 Lebensmittel, Trinkwasser": 2
      },
      "by_global_category": {
        "8.10.130.10.10 Lebensmittelaufsicht": 2
      }
    }
  },
  "by_topic_tree": [
    {
      "identifier": "8",
      "title": "Gesundheit, Soziale Sicherheit",
      "total": 2,
      "own": 0,
      "by_type": {
        "Anderes": 2
      },
      "children": [
        {
          "identifier": "81",
          "title": "Krankenanstalten, Rettungswesen, Umweltschutz",
          "total": 2,
          "own": 0,
          "by_type": {
            "Anderes": 2
          },
          "children": [
            {
              "identifier": "817",
              "title": "Lebensmittel, Trinkwasser",
              "total": 2,
              "own": 2,
              "by_type": {
                "Anderes": 2
              }
            }
          ]
        }
      ]
    }
  ],
  "by_global_category_tree": [
    {
      "identifier": "8",
      "title": "Gesundheitswesen, Arbeit, Sozialversicherungen, Wohnen, Sozialhilfe",
      "total": 2,
      "own": 0,
      "by_type": {
        "Anderes": 2
      },
      "children": [
        {
          "identifier": "8.10",
          "title": "Gesundheitswesen",
          "total": 2,
          "own": 0,
          "by_type": {
            "Anderes": 2
          },
          "children": [
            {
              "identifier": "8.10.130",
              "title": "Hygiene",
              "total": 2,
              "own": 0,
              "by_type": {
                "Anderes": 2
              },
              "children": [
                {
                  "identifier": "8.10.130.10",
                  "title": "Lebensmittel und Gebrauchsgegenstände",
                  "total": 2,
                  "own": 0,
                  "by_type": {
                    "Anderes": 2
                  },
                  "children": [
                    {
                      "identifier": "8.10.130.10.10",
                      "title": "Lebensmittelaufsicht",
                      "total": 2,
                      "own": 2,
                      "by_type": {
                        "Anderes": 2
                      }
                    }
                  ]
                }
              ]
            }
          ]
        }
      ]
    }
  ],
  "by_language": {
    "de": 1,
    "fr": 1
  }
}